Workbook

Sheet Summary
A1: OWASP ASVS 5.0 – Compliance Tracker
A5: Chapter | B5: Total Reqs | C5: L1 Total | D5: L1 Compliant | E5: L1 % | F5: L2 Total | G5: L2 Compliant | H5: L2 % | I5: L3 Total | J5: L3 Compliant | K5: L3 % | L5: Overall Compliant | M5: Overall %
A6: V1 – Encoding and Sanitization | B6: 30 | C6: 8 | D6: =COUNTIFS('V1 - Encoding and Sanitization'!$F$2:$F$36,"Compliant",'V1 - Encoding and Sanitization'!$E$2:$E$36,1) | E6: =IF(C6=0,"",D6/C6) | F6: 19 | G6: =COUNTIFS('V1 - Encoding and Sanitization'!$F$2:$F$36,"Compliant",'V1 - Encoding and Sanitization'!$E$2:$E$36,2) | H6: =IF(F6=0,"",G6/F6) | I6: 3 | J6: =COUNTIFS('V1 - Encoding and Sanitization'!$F$2:$F$36,"Compliant",'V1 - Encoding and Sanitization'!$E$2:$E$36,3) | K6: =IF(I6=0,"",J6/I6) | L6: =COUNTIF('V1 - Encoding and Sanitization'!$F$2:$F$36,"Compliant") | M6: =IF(B6=0,"",L6/B6)
A7: V2 – Validation and Business Logic | B7: 13 | C7: 4 | D7: =COUNTIFS('V2 - Validation and Business Lo'!$F$2:$F$18,"Compliant",'V2 - Validation and Business Lo'!$E$2:$E$18,1) | E7: =IF(C7=0,"",D7/C7) | F7: 7 | G7: =COUNTIFS('V2 - Validation and Business Lo'!$F$2:$F$18,"Compliant",'V2 - Validation and Business Lo'!$E$2:$E$18,2) | H7: =IF(F7=0,"",G7/F7) | I7: 2 | J7: =COUNTIFS('V2 - Validation and Business Lo'!$F$2:$F$18,"Compliant",'V2 - Validation and Business Lo'!$E$2:$E$18,3) | K7: =IF(I7=0,"",J7/I7) | L7: =COUNTIF('V2 - Validation and Business Lo'!$F$2:$F$18,"Compliant") | M7: =IF(B7=0,"",L7/B7)
A8: V3 – Web Frontend Security | B8: 31 | C8: 8 | D8: =COUNTIFS('V3 - Web Frontend Security'!$F$2:$F$39,"Compliant",'V3 - Web Frontend Security'!$E$2:$E$39,1) | E8: =IF(C8=0,"",D8/C8) | F8: 11 | G8: =COUNTIFS('V3 - Web Frontend Security'!$F$2:$F$39,"Compliant",'V3 - Web Frontend Security'!$E$2:$E$39,2) | H8: =IF(F8=0,"",G8/F8) | I8: 12 | J8: =COUNTIFS('V3 - Web Frontend Security'!$F$2:$F$39,"Compliant",'V3 - Web Frontend Security'!$E$2:$E$39,3) | K8: =IF(I8=0,"",J8/I8) | L8: =COUNTIF('V3 - Web Frontend Security'!$F$2:$F$39,"Compliant") | M8: =IF(B8=0,"",L8/B8)
A9: V4 – API and Web Service | B9: 16 | C9: 2 | D9: =COUNTIFS('V4 - API and Web Service'!$F$2:$F$21,"Compliant",'V4 - API and Web Service'!$E$2:$E$21,1) | E9: =IF(C9=0,"",D9/C9) | F9: 8 | G9: =COUNTIFS('V4 - API and Web Service'!$F$2:$F$21,"Compliant",'V4 - API and Web Service'!$E$2:$E$21,2) | H9: =IF(F9=0,"",G9/F9) | I9: 6 | J9: =COUNTIFS('V4 - API and Web Service'!$F$2:$F$21,"Compliant",'V4 - API and Web Service'!$E$2:$E$21,3) | K9: =IF(I9=0,"",J9/I9) | L9: =COUNTIF('V4 - API and Web Service'!$F$2:$F$21,"Compliant") | M9: =IF(B9=0,"",L9/B9)
A10: V5 – File Handling | B10: 13 | C10: 4 | D10: =COUNTIFS('V5 - File Handling'!$F$2:$F$18,"Compliant",'V5 - File Handling'!$E$2:$E$18,1) | E10: =IF(C10=0,"",D10/C10) | F10: 5 | G10: =COUNTIFS('V5 - File Handling'!$F$2:$F$18,"Compliant",'V5 - File Handling'!$E$2:$E$18,2) | H10: =IF(F10=0,"",G10/F10) | I10: 4 | J10: =COUNTIFS('V5 - File Handling'!$F$2:$F$18,"Compliant",'V5 - File Handling'!$E$2:$E$18,3) | K10: =IF(I10=0,"",J10/I10) | L10: =COUNTIF('V5 - File Handling'!$F$2:$F$18,"Compliant") | M10: =IF(B10=0,"",L10/B10)
A11: V6 – Authentication | B11: 47 | C11: 13 | D11: =COUNTIFS('V6 - Authentication'!$F$2:$F$56,"Compliant",'V6 - Authentication'!$E$2:$E$56,1) | E11: =IF(C11=0,"",D11/C11) | F11: 22 | G11: =COUNTIFS('V6 - Authentication'!$F$2:$F$56,"Compliant",'V6 - Authentication'!$E$2:$E$56,2) | H11: =IF(F11=0,"",G11/F11) | I11: 12 | J11: =COUNTIFS('V6 - Authentication'!$F$2:$F$56,"Compliant",'V6 - Authentication'!$E$2:$E$56,3) | K11: =IF(I11=0,"",J11/I11) | L11: =COUNTIF('V6 - Authentication'!$F$2:$F$56,"Compliant") | M11: =IF(B11=0,"",L11/B11)
A12: V7 – Session Management | B12: 19 | C12: 6 | D12: =COUNTIFS('V7 - Session Management'!$F$2:$F$26,"Compliant",'V7 - Session Management'!$E$2:$E$26,1) | E12: =IF(C12=0,"",D12/C12) | F12: 12 | G12: =COUNTIFS('V7 - Session Management'!$F$2:$F$26,"Compliant",'V7 - Session Management'!$E$2:$E$26,2) | H12: =IF(F12=0,"",G12/F12) | I12: 1 | J12: =COUNTIFS('V7 - Session Management'!$F$2:$F$26,"Compliant",'V7 - Session Management'!$E$2:$E$26,3) | K12: =IF(I12=0,"",J12/I12) | L12: =COUNTIF('V7 - Session Management'!$F$2:$F$26,"Compliant") | M12: =IF(B12=0,"",L12/B12)
A13: V8 – Authorization | B13: 13 | C13: 4 | D13: =COUNTIFS('V8 - Authorization'!$F$2:$F$18,"Compliant",'V8 - Authorization'!$E$2:$E$18,1) | E13: =IF(C13=0,"",D13/C13) | F13: 3 | G13: =COUNTIFS('V8 - Authorization'!$F$2:$F$18,"Compliant",'V8 - Authorization'!$E$2:$E$18,2) | H13: =IF(F13=0,"",G13/F13) | I13: 6 | J13: =COUNTIFS('V8 - Authorization'!$F$2:$F$18,"Compliant",'V8 - Authorization'!$E$2:$E$18,3) | K13: =IF(I13=0,"",J13/I13) | L13: =COUNTIF('V8 - Authorization'!$F$2:$F$18,"Compliant") | M13: =IF(B13=0,"",L13/B13)
A14: V9 – Self-contained Tokens | B14: 7 | C14: 4 | D14: =COUNTIFS('V9 - Self-contained Tokens'!$F$2:$F$10,"Compliant",'V9 - Self-contained Tokens'!$E$2:$E$10,1) | E14: =IF(C14=0,"",D14/C14) | F14: 3 | G14: =COUNTIFS('V9 - Self-contained Tokens'!$F$2:$F$10,"Compliant",'V9 - Self-contained Tokens'!$E$2:$E$10,2) | H14: =IF(F14=0,"",G14/F14) | I14: 0 | J14: N/A | K14: N/A | L14: =COUNTIF('V9 - Self-contained Tokens'!$F$2:$F$10,"Compliant") | M14: =IF(B14=0,"",L14/B14)
A15: V10 – OAuth and OIDC | B15: 36 | C15: 5 | D15: =COUNTIFS('V10 - OAuth and OIDC'!$F$2:$F$44,"Compliant",'V10 - OAuth and OIDC'!$E$2:$E$44,1) | E15: =IF(C15=0,"",D15/C15) | F15: 24 | G15: =COUNTIFS('V10 - OAuth and OIDC'!$F$2:$F$44,"Compliant",'V10 - OAuth and OIDC'!$E$2:$E$44,2) | H15: =IF(F15=0,"",G15/F15) | I15: 7 | J15: =COUNTIFS('V10 - OAuth and OIDC'!$F$2:$F$44,"Compliant",'V10 - OAuth and OIDC'!$E$2:$E$44,3) | K15: =IF(I15=0,"",J15/I15) | L15: =COUNTIF('V10 - OAuth and OIDC'!$F$2:$F$44,"Compliant") | M15: =IF(B15=0,"",L15/B15)
A16: V11 – Cryptography | B16: 24 | C16: 3 | D16: =COUNTIFS('V11 - Cryptography'!$F$2:$F$32,"Compliant",'V11 - Cryptography'!$E$2:$E$32,1) | E16: =IF(C16=0,"",D16/C16) | F16: 11 | G16: =COUNTIFS('V11 - Cryptography'!$F$2:$F$32,"Compliant",'V11 - Cryptography'!$E$2:$E$32,2) | H16: =IF(F16=0,"",G16/F16) | I16: 10 | J16: =COUNTIFS('V11 - Cryptography'!$F$2:$F$32,"Compliant",'V11 - Cryptography'!$E$2:$E$32,3) | K16: =IF(I16=0,"",J16/I16) | L16: =COUNTIF('V11 - Cryptography'!$F$2:$F$32,"Compliant") | M16: =IF(B16=0,"",L16/B16)
A17: V12 – Secure Communication | B17: 12 | C17: 3 | D17: =COUNTIFS('V12 - Secure Communication'!$F$2:$F$16,"Compliant",'V12 - Secure Communication'!$E$2:$E$16,1) | E17: =IF(C17=0,"",D17/C17) | F17: 6 | G17: =COUNTIFS('V12 - Secure Communication'!$F$2:$F$16,"Compliant",'V12 - Secure Communication'!$E$2:$E$16,2) | H17: =IF(F17=0,"",G17/F17) | I17: 3 | J17: =COUNTIFS('V12 - Secure Communication'!$F$2:$F$16,"Compliant",'V12 - Secure Communication'!$E$2:$E$16,3) | K17: =IF(I17=0,"",J17/I17) | L17: =COUNTIF('V12 - Secure Communication'!$F$2:$F$16,"Compliant") | M17: =IF(B17=0,"",L17/B17)
A18: V13 – Configuration | B18: 21 | C18: 1 | D18: =COUNTIFS('V13 - Configuration'!$F$2:$F$26,"Compliant",'V13 - Configuration'!$E$2:$E$26,1) | E18: =IF(C18=0,"",D18/C18) | F18: 12 | G18: =COUNTIFS('V13 - Configuration'!$F$2:$F$26,"Compliant",'V13 - Configuration'!$E$2:$E$26,2) | H18: =IF(F18=0,"",G18/F18) | I18: 8 | J18: =COUNTIFS('V13 - Configuration'!$F$2:$F$26,"Compliant",'V13 - Configuration'!$E$2:$E$26,3) | K18: =IF(I18=0,"",J18/I18) | L18: =COUNTIF('V13 - Configuration'!$F$2:$F$26,"Compliant") | M18: =IF(B18=0,"",L18/B18)
A19: V14 – Data Protection | B19: 13 | C19: 2 | D19: =COUNTIFS('V14 - Data Protection'!$F$2:$F$17,"Compliant",'V14 - Data Protection'!$E$2:$E$17,1) | E19: =IF(C19=0,"",D19/C19) | F19: 7 | G19: =COUNTIFS('V14 - Data Protection'!$F$2:$F$17,"Compliant",'V14 - Data Protection'!$E$2:$E$17,2) | H19: =IF(F19=0,"",G19/F19) | I19: 4 | J19: =COUNTIFS('V14 - Data Protection'!$F$2:$F$17,"Compliant",'V14 - Data Protection'!$E$2:$E$17,3) | K19: =IF(I19=0,"",J19/I19) | L19: =COUNTIF('V14 - Data Protection'!$F$2:$F$17,"Compliant") | M19: =IF(B19=0,"",L19/B19)
A20: V15 – Secure Coding and Architecture | B20: 21 | C20: 3 | D20: =COUNTIFS('V15 - Secure Coding and Archite'!$F$2:$F$26,"Compliant",'V15 - Secure Coding and Archite'!$E$2:$E$26,1) | E20: =IF(C20=0,"",D20/C20) | F20: 10 | G20: =COUNTIFS('V15 - Secure Coding and Archite'!$F$2:$F$26,"Compliant",'V15 - Secure Coding and Archite'!$E$2:$E$26,2) | H20: =IF(F20=0,"",G20/F20) | I20: 8 | J20: =COUNTIFS('V15 - Secure Coding and Archite'!$F$2:$F$26,"Compliant",'V15 - Secure Coding and Archite'!$E$2:$E$26,3) | K20: =IF(I20=0,"",J20/I20) | L20: =COUNTIF('V15 - Secure Coding and Archite'!$F$2:$F$26,"Compliant") | M20: =IF(B20=0,"",L20/B20)
A21: V16 – Security Logging and Error Handling | B21: 17 | C21: 0 | D21: N/A | E21: N/A | F21: 16 | G21: =COUNTIFS('V16 - Security Logging and Erro'!$F$2:$F$23,"Compliant",'V16 - Security Logging and Erro'!$E$2:$E$23,2) | H21: =IF(F21=0,"",G21/F21) | I21: 1 | J21: =COUNTIFS('V16 - Security Logging and Erro'!$F$2:$F$23,"Compliant",'V16 - Security Logging and Erro'!$E$2:$E$23,3) | K21: =IF(I21=0,"",J21/I21) | L21: =COUNTIF('V16 - Security Logging and Erro'!$F$2:$F$23,"Compliant") | M21: =IF(B21=0,"",L21/B21)
A22: V17 – WebRTC | B22: 12 | C22: 0 | D22: N/A | E22: N/A | F22: 7 | G22: =COUNTIFS('V17 - WebRTC'!$F$2:$F$16,"Compliant",'V17 - WebRTC'!$E$2:$E$16,2) | H22: =IF(F22=0,"",G22/F22) | I22: 5 | J22: =COUNTIFS('V17 - WebRTC'!$F$2:$F$16,"Compliant",'V17 - WebRTC'!$E$2:$E$16,3) | K22: =IF(I22=0,"",J22/I22) | L22: =COUNTIF('V17 - WebRTC'!$F$2:$F$16,"Compliant") | M22: =IF(B22=0,"",L22/B22)
A23: TOTAL | B23: =SUM(B6:B22) | C23: =SUM(C6:C22) | D23: =SUM(D6:D22) | E23: =IFERROR(AVERAGE(E6:E22),"") | F23: =SUM(F6:F22) | G23: =SUM(G6:G22) | H23: =IFERROR(AVERAGE(H6:H22),"") | I23: =SUM(I6:I22) | J23: =SUM(J6:J22) | K23: =IFERROR(AVERAGE(K6:K22),"") | L23: =SUM(L6:L22) | M23: =IFERROR(AVERAGE(M6:M22),"")

Sheet ASVS DX Guide
A1: ASVS Tracker DX Guide
A2: What is automated? | B2: make asvs-tracker runs evidence tests, copies the source workbook, scans repository evidence, infers each ASVS row, and writes this filled workbook.
A3: Input source | B3: The Excel template is the source of ASVS rows. The markdown tracker is not read or required.
A4: Important limitation | B4: The automation is deterministic: it can infer from tests, source, configuration, and build artifacts, but a new control may need a new targeted test/evidence rule before it becomes Compliant.
A6: Status | B6: Meaning | C6: When generated | D6: Next action
A7: Compliant | B7: The row has matching implementation/configuration/build evidence and the evidence test run passed. | C7: Generated when direct automated evidence or source evidence matches the ASVS row. | D7: Keep make asvs-tracker passing and update tests when scope changes.
A8: Planned | B8: The row is relevant but not yet strongly proven by repository evidence. | C8: Generated when the row has no direct matching evidence or only weak/reference evidence. | D8: Implement the control or add a targeted test/evidence rule.
A9: N/A | B9: The row is outside the current backend/API scope. | C9: Generated for absent technologies such as frontend DOM, OAuth/OIDC, GraphQL, XML/SOAP, WebRTC, or file upload surfaces. | D9: Revisit if that technology enters scope.
A11: DX column | B11: Purpose | C11: Example
A12: DX Status Meaning | B12: Plain-language explanation of the generated status. | C12: Compliant means repository evidence matched and tests passed.
A13: Evidence Type | B13: Shows whether support is automated, referenced, scope-based, or missing. | C13: Automated repository evidence
A14: Automated Evidence | B14: Mapped tests, code features, or build artifacts supporting the row. | C14: RbacIntegrationTest; Spring method security and RBAC annotations detected
A15: Evidence Source | B15: The security topic inferred from ASVS text and SR/AC references. | C15: RBAC roles and endpoint isolation
A16: Next Action | B16: What to do to move the row forward. | C16: Add implementation/tests that directly prove this ASVS row.
A18: Recommended commands | B18: make asvs-tracker | C18: Runs tests and regenerates the filled Excel.
A19: Recommended commands | B19: make asvs-fill | C19: Regenerates Excel from existing reports without rerunning tests.

Sheet V1 - Encoding and Sanitization
A1: Section ID | B1: Section Name | C1: Req ID | D1: Description | E1: Level | F1: Status | G1: Observations | H1: Reference / Link | I1: DX Status Meaning | J1: Evidence Type | K1: Automated Evidence | L1: Evidence Source | M1: Next Action
A2: V1.1 | B2: Encoding and Sanitization Architecture
A3: V1.1 | B3: Encoding and Sanitization Architecture | C3: V1.1.1 | D3: Verify that input is decoded or unescaped into a canonical form only once, it is only decoded when encoded data in that form is expected, and that this is done before processing the input further, for example it is not performed after input validation or sanitization. | E3: 2 | F3: Compliant | G3: Automatically marked compliant from passing evidence: server-side price enforcement; stock limit validation; input shape/range validation; unknown-field rejection; payload/request limit coverage. | H3: SR-24; SR-25; SR-28; SR-29; SR-30; SaleServiceTest; AbuseCaseRegressionTest; SlotServiceTest; ControllerIntegrationTests; SystemFunctionalTests; ControllerUnitTests; GlobalExceptionHandlerTest; application.properties; Bean Validation and request-shape controls detected | I3: Automatically inferred as implemented or justified from passing tests, source code, configuration, or build artifacts. | J3: Automated repository evidence | K3: SaleServiceTest; AbuseCaseRegressionTest; SlotServiceTest; ControllerIntegrationTests; SystemFunctionalTests; ControllerUnitTests; GlobalExceptionHandlerTest; application.properties; Bean Validation and request-shape controls detected | L3: server-side price enforcement; stock limit validation; input shape/range validation; unknown-field rejection; payload/request limit coverage | M3: Keep make asvs-tracker passing; reassess if code, tests, or scope changes.
A4: V1.1 | B4: Encoding and Sanitization Architecture | C4: V1.1.2 | D4: Verify that the application performs output encoding and escaping either as a final step before being used by the interpreter for which it is intended or by the interpreter itself. | E4: 2 | F4: Compliant | G4: Automatically marked compliant from passing evidence: DTO response boundaries and unknown-field rejection. | H4: SR-16; ControllerUnitTests; GlobalExceptionHandlerTest | I4: Automatically inferred as implemented or justified from passing tests, source code, configuration, or build artifacts. | J4: Automated repository evidence | K4: ControllerUnitTests; GlobalExceptionHandlerTest | L4: DTO response boundaries and unknown-field rejection | M4: Keep make asvs-tracker passing; reassess if code, tests, or scope changes.
A5: V1.2 | B5: Injection Prevention
A6: V1.2 | B6: Injection Prevention | C6: V1.2.1 | D6: Verify that output encoding for an HTTP response, HTML document, or XML document is relevant for the context required, such as encoding the relevant characters for HTML elements, HTML attributes, HTML comments, CSS, or HTTP header fields, to avoid changing the message or document structure. | E6: 1 | F6: N/A | G6: Automatically marked out of scope: No browser-rendered frontend surface is present in this repository. | H6: Automated scope inference | I6: Out of scope for VendNet as currently implemented, or the requirement does not apply to this REST API/backend. | J6: Scope inference | K6: Not required for current backend scope. | L6: No browser-rendered frontend surface is present in this repository. | M6: Revisit if the application scope changes.
A7: V1.2 | B7: Injection Prevention | C7: V1.2.2 | D7: Verify that when dynamically building URLs, untrusted data is encoded according to its context (e.g., URL encoding or base64url encoding for query or path parameters). Ensure that only safe URL protocols are permitted (e.g., disallow javascript: or data:). | E7: 1 | F7: N/A | G7: Automatically marked out of scope: No browser-rendered frontend surface is present in this repository. | H7: Automated scope inference | I7: Out of scope for VendNet as currently implemented, or the requirement does not apply to this REST API/backend. | J7: Scope inference | K7: Not required for current backend scope. | L7: No browser-rendered frontend surface is present in this repository. | M7: Revisit if the application scope changes.
A8: V1.2 | B8: Injection Prevention | C8: V1.2.3 | D8: Verify that output encoding or escaping is used when dynamically building JavaScript content (including JSON), to avoid changing the message or document structure (to avoid JavaScript and JSON injection). | E8: 1 | F8: N/A | G8: Automatically marked out of scope: No browser-rendered frontend surface is present in this repository. | H8: Automated scope inference | I8: Out of scope for VendNet as currently implemented, or the requirement does not apply to this REST API/backend. | J8: Scope inference | K8: Not required for current backend scope. | L8: No browser-rendered frontend surface is present in this repository. | M8: Revisit if the application scope changes.
A9: V1.2 | B9: Injection Prevention | C9: V1.2.4 | D9: Verify that data selection or database queries (e.g., SQL, HQL, NoSQL, Cypher) use parameterized queries, ORMs, entity frameworks, or are otherwise protected from SQL Injection and other database injection attacks. This is also relevant when writing stored procedures. | E9: 1 | F9: Compliant | G9: Automatically marked compliant from passing evidence: SQL injection regression and taint checks; SQL injection abuse-case regression. | H9: SR-09; AC-05; AbuseCaseRegressionTest; IastIntegrationTest | I9: Automatically inferred as implemented or justified from passing tests, source code, configuration, or build artifacts. | J9: Automated repository evidence | K9: AbuseCaseRegressionTest; IastIntegrationTest | L9: SQL injection regression and taint checks; SQL injection abuse-case regression | M9: Keep make asvs-tracker passing; reassess if code, tests, or scope changes.
A10: V1.2 | B10: Injection Prevention | C10: V1.2.5 | D10: Verify that the application protects against OS command injection and that operating system calls use parameterized OS queries or use contextual command line output encoding. | E10: 1 | F10: Compliant | G10: Automatically marked compliant from passing evidence: SQL injection regression and taint checks; SQL injection abuse-case regression. | H10: SR-09; AC-05; AbuseCaseRegressionTest; IastIntegrationTest | I10: Automatically inferred as implemented or justified from passing tests, source code, configuration, or build artifacts. | J10: Automated repository evidence | K10: AbuseCaseRegressionTest; IastIntegrationTest | L10: SQL injection regression and taint checks; SQL injection abuse-case regression | M10: Keep make asvs-tracker passing; reassess if code, tests, or scope changes.
A11: V1.2 | B11: Injection Prevention | C11: V1.2.6 | D11: Verify that the application protects against LDAP injection vulnerabilities, or that specific security controls to prevent LDAP injection have been implemented. | E11: 2 | F11: Compliant | G11: Automatically marked compliant from passing evidence: SQL injection regression and taint checks; SQL injection abuse-case regression. | H11: SR-09; AC-05; AbuseCaseRegressionTest; IastIntegrationTest | I11: Automatically inferred as implemented or justified from passing tests, source code, configuration, or build artifacts. | J11: Automated repository evidence | K11: AbuseCaseRegressionTest; IastIntegrationTest | L11: SQL injection regression and taint checks; SQL injection abuse-case regression | M11: Keep make asvs-tracker passing; reassess if code, tests, or scope changes.
A12: V1.2 | B12: Injection Prevention | C12: V1.2.7 | D12: Verify that the application is protected against XPath injection attacks by using query parameterization or precompiled queries. | E12: 2 | F12: Compliant | G12: Automatically marked compliant from passing evidence: SQL injection regression and taint checks; SQL injection abuse-case regression; path traversal and report sandboxing; unsafe path/link handling; path traversal abuse-case regression. | H12: SR-09; AC-05; SR-26; SR-27; AC-06; AbuseCaseRegressionTest; IastIntegrationTest; PathValidatorImplTest; ReportDirectoryServiceImplTest; path validation and report sandbox code detected | I12: Automatically inferred as implemented or justified from passing tests, source code, configuration, or build artifacts. | J12: Automated repository evidence | K12: AbuseCaseRegressionTest; IastIntegrationTest; PathValidatorImplTest; ReportDirectoryServiceImplTest; path validation and report sandbox code detected | L12: SQL injection regression and taint checks; SQL injection abuse-case regression; path traversal and report sandboxing; unsafe path/link handling; path traversal abuse-case regression | M12: Keep make asvs-tracker passing; reassess if code, tests, or scope changes.
A13: V1.2 | B13: Injection Prevention | C13: V1.2.8 | D13: Verify that LaTeX processors are configured securely (such as not using the "--shell-escape" flag) and an allowlist of commands is used to prevent LaTeX injection attacks. | E13: 2 | F13: Compliant | G13: Automatically marked compliant from passing evidence: SQL injection regression and taint checks; SQL injection abuse-case regression. | H13: SR-09; AC-05; AbuseCaseRegressionTest; IastIntegrationTest | I13: Automatically inferred as implemented or justified from passing tests, source code, configuration, or build artifacts. | J13: Automated repository evidence | K13: AbuseCaseRegressionTest; IastIntegrationTest | L13: SQL injection regression and taint checks; SQL injection abuse-case regression | M13: Keep make asvs-tracker passing; reassess if code, tests, or scope changes.
A14: V1.2 | B14: Injection Prevention | C14: V1.2.9 | D14: Verify that the application escapes special characters in regular expressions (typically using a backslash) to prevent them from being misinterpreted as metacharacters. | E14: 2 | F14: Compliant | G14: Automatically marked compliant from passing evidence: path traversal and report sandboxing. | H14: SR-26; PathValidatorImplTest; ReportDirectoryServiceImplTest; AbuseCaseRegressionTest; path validation and report sandbox code detected | I14: Automatically inferred as implemented or justified from passing tests, source code, configuration, or build artifacts. | J14: Automated repository evidence | K14: PathValidatorImplTest; ReportDirectoryServiceImplTest; AbuseCaseRegressionTest; path validation and report sandbox code detected | L14: path traversal and report sandboxing | M14: Keep make asvs-tracker passing; reassess if code, tests, or scope changes.
A15: V1.2 | B15: Injection Prevention | C15: V1.2.10 | D15: Verify that the application is protected against CSV and Formula Injection. The application must follow the escaping rules defined in RFC 4180 sections 2.6 and 2.7 when exporting CSV content. Additionally, when exporting to CSV or other spreadsheet formats (such as XLS, XLSX, or ODF), special characters (including '=', '+', '-', '@', '\t' (tab), and '\0' (null character)) must be escaped with a single quote if they appear as the first character in a field value. | E15: 3 | F15: Compliant | G15: Automatically marked compliant from passing evidence: SQL injection regression and taint checks; SQL injection abuse-case regression. | H15: SR-09; AC-05; AbuseCaseRegressionTest; IastIntegrationTest | I15: Automatically inferred as implemented or justified from passing tests, source code, configuration, or build artifacts. | J15: Automated repository evidence | K15: AbuseCaseRegressionTest; IastIntegrationTest | L15: SQL injection regression and taint checks; SQL injection abuse-case regression | M15: Keep make asvs-tracker passing; reassess if code, tests, or scope changes.
A16: V1.3 | B16: Sanitization
A17: V1.3 | B17: Sanitization | C17: V1.3.1 | D17: Verify that all untrusted HTML input from WYSIWYG editors or similar is sanitized using a well-known and secure HTML sanitization library or framework feature. | E17: 1 | F17: N/A | G17: Automatically marked out of scope: No browser-rendered frontend surface is present in this repository. | H17: Automated scope inference | I17: Out of scope for VendNet as currently implemented, or the requirement does not apply to this REST API/backend. | J17: Scope inference | K17: Not required for current backend scope. | L17: No browser-rendered frontend surface is present in this repository. | M17: Revisit if the application scope changes.
A18: V1.3 | B18: Sanitization | C18: V1.3.2 | D18: Verify that the application avoids the use of eval() or other dynamic code execution features such as Spring Expression Language (SpEL). Where there is no alternative, any user input being included must be sanitized before being executed. | E18: 1 | F18: Compliant | G18: Automatically marked compliant from passing evidence: input shape/range validation; unknown-field rejection; payload/request limit coverage. | H18: SR-28; SR-29; SR-30; ControllerIntegrationTests; SystemFunctionalTests; ControllerUnitTests; GlobalExceptionHandlerTest; application.properties; Bean Validation and request-shape controls detected | I18: Automatically inferred as implemented or justified from passing tests, source code, configuration, or build artifacts. | J18: Automated repository evidence | K18: ControllerIntegrationTests; SystemFunctionalTests; ControllerUnitTests; GlobalExceptionHandlerTest; application.properties; Bean Validation and request-shape controls detected | L18: input shape/range validation; unknown-field rejection; payload/request limit coverage | M18: Keep make asvs-tracker passing; reassess if code, tests, or scope changes.
A19: V1.3 | B19: Sanitization | C19: V1.3.3 | D19: Verify that data being passed to a potentially dangerous context is sanitized beforehand to enforce safety measures, such as only allowing characters which are safe for this context and trimming input which is too long. | E19: 2 | F19: Compliant | G19: Automatically marked compliant from passing evidence: input shape/range validation; payload/request limit coverage; unknown-field rejection. | H19: SR-28; SR-30; SR-29; ControllerIntegrationTests; SystemFunctionalTests; application.properties; ControllerUnitTests; GlobalExceptionHandlerTest; Bean Validation and request-shape controls detected | I19: Automatically inferred as implemented or justified from passing tests, source code, configuration, or build artifacts. | J19: Automated repository evidence | K19: ControllerIntegrationTests; SystemFunctionalTests; application.properties; ControllerUnitTests; GlobalExceptionHandlerTest; Bean Validation and request-shape controls detected | L19: input shape/range validation; payload/request limit coverage; unknown-field rejection | M19: Keep make asvs-tracker passing; reassess if code, tests, or scope changes.
A20: V1.3 | B20: Sanitization | C20: V1.3.4 | D20: Verify that user-supplied Scalable Vector Graphics (SVG) scriptable content is validated or sanitized to contain only tags and attributes (such as draw graphics) that are safe for the application, e.g., do not contain scripts and foreignObject. | E20: 2 | F20: Planned | G20: Automatically marked planned because no direct implementation, test, or scope exemption matched this ASVS row. | H20: Automated inference found no strong repository evidence | I20: Automatically inferred as required or potentially relevant, but not yet proven by strong repository evidence. | J20: Evidence needed | K20: No direct automated evidence matched this ASVS row. | L20: ASVS row V1.3.4; level 2 | M20: Implement the control or add a targeted test/evidence rule, then rerun make asvs-tracker.
A21: V1.3 | B21: Sanitization | C21: V1.3.5 | D21: Verify that the application sanitizes or disables user-supplied scriptable or expression template language content, such as Markdown, CSS or XSL stylesheets, BBCode, or similar. | E21: 2 | F21: N/A | G21: Automatically marked out of scope: No browser-rendered frontend surface is present in this repository. | H21: Automated scope inference | I21: Out of scope for VendNet as currently implemented, or the requirement does not apply to this REST API/backend. | J21: Scope inference | K21: Not required for current backend scope. | L21: No browser-rendered frontend surface is present in this repository. | M21: Revisit if the application scope changes.
A22: V1.3 | B22: Sanitization | C22: V1.3.6 | D22: Verify that the application protects against Server-side Request Forgery (SSRF) attacks, by validating untrusted data against an allowlist of protocols, domains, paths and ports and sanitizing potentially dangerous characters before using the data to call another service. | E22: 2 | F22: N/A | G22: Automatically marked out of scope: No browser-rendered frontend surface is present in this repository. | H22: Automated scope inference | I22: Out of scope for VendNet as currently implemented, or the requirement does not apply to this REST API/backend. | J22: Scope inference | K22: Not required for current backend scope. | L22: No browser-rendered frontend surface is present in this repository. | M22: Revisit if the application scope changes.
A23: V1.3 | B23: Sanitization | C23: V1.3.7 | D23: Verify that the application protects against template injection attacks by not allowing templates to be built based on untrusted input. Where there is no alternative, any untrusted input being included dynamically during template creation must be sanitized or strictly validated. | E23: 2 | F23: Compliant | G23: Automatically marked compliant from passing evidence: input shape/range validation; unknown-field rejection; payload/request limit coverage; SQL injection regression and taint checks; SQL injection abuse-case regression. | H23: SR-28; SR-29; SR-30; SR-09; AC-05; ControllerIntegrationTests; SystemFunctionalTests; ControllerUnitTests; GlobalExceptionHandlerTest; application.properties; AbuseCaseRegressionTest; IastIntegrationTest; Bean Validation and request-shape controls detected | I23: Automatically inferred as implemented or justified from passing tests, source code, configuration, or build artifacts. | J23: Automated repository evidence | K23: ControllerIntegrationTests; SystemFunctionalTests; ControllerUnitTests; GlobalExceptionHandlerTest; application.properties; AbuseCaseRegressionTest; IastIntegrationTest; Bean Validation and request-shape controls detected | L23: input shape/range validation; unknown-field rejection; payload/request limit coverage; SQL injection regression and taint checks; SQL injection abuse-case regression | M23: Keep make asvs-tracker passing; reassess if code, tests, or scope changes.
A24: V1.3 | B24: Sanitization | C24: V1.3.8 | D24: Verify that the application appropriately sanitizes untrusted input before use in Java Naming and Directory Interface (JNDI) queries and that JNDI is configured securely to prevent JNDI injection attacks. | E24: 2 | F24: Compliant | G24: Automatically marked compliant from passing evidence: input shape/range validation; unknown-field rejection; payload/request limit coverage; SQL injection regression and taint checks; SQL injection abuse-case regression; path traversal and report sandboxing; unsafe path/link handling; path traversal abuse-case regression. | H24: SR-28; SR-29; SR-30; SR-09; AC-05; SR-26; SR-27; AC-06; ControllerIntegrationTests; SystemFunctionalTests; ControllerUnitTests; GlobalExceptionHandlerTest; application.properties; AbuseCaseRegressionTest; IastIntegrationTest; PathValidatorImplTest; ReportDirectoryServiceImplTest; Bean Validation and request-shape controls detected; path validation and report sandbox code detected | I24: Automatically inferred as implemented or justified from passing tests, source code, configuration, or build artifacts. | J24: Automated repository evidence | K24: ControllerIntegrationTests; SystemFunctionalTests; ControllerUnitTests; GlobalExceptionHandlerTest; application.properties; AbuseCaseRegressionTest; IastIntegrationTest; PathValidatorImplTest; ReportDirectoryServiceImplTest; Bean Validation and request-shape controls detected; path validation and report sandbox code detected | L24: input shape/range validation; unknown-field rejection; payload/request limit coverage; SQL injection regression and taint checks; SQL injection abuse-case regression; path traversal and report sandboxing; unsafe path/link handling; path traversal abuse-case regression | M24: Keep make asvs-tracker passing; reassess if code, tests, or scope changes.
A25: V1.3 | B25: Sanitization | C25: V1.3.9 | D25: Verify that the application sanitizes content before it is sent to memcache to prevent injection attacks. | E25: 2 | F25: Compliant | G25: Automatically marked compliant from passing evidence: SQL injection regression and taint checks; SQL injection abuse-case regression. | H25: SR-09; AC-05; AbuseCaseRegressionTest; IastIntegrationTest | I25: Automatically inferred as implemented or justified from passing tests, source code, configuration, or build artifacts. | J25: Automated repository evidence | K25: AbuseCaseRegressionTest; IastIntegrationTest | L25: SQL injection regression and taint checks; SQL injection abuse-case regression | M25: Keep make asvs-tracker passing; reassess if code, tests, or scope changes.
A26: V1.3 | B26: Sanitization | C26: V1.3.10 | D26: Verify that format strings which might resolve in an unexpected or malicious way when used are sanitized before being processed. | E26: 2 | F26: N/A | G26: Automatically marked out of scope: No user-controlled printf-style format-string execution path is present in the Java REST backend. | H26: Automated scope inference | I26: Out of scope for VendNet as currently implemented, or the requirement does not apply to this REST API/backend. | J26: Scope inference | K26: Not required for current backend scope. | L26: No user-controlled printf-style format-string execution path is present in the Java REST backend. | M26: Revisit if the application scope changes.
A27: V1.3 | B27: Sanitization | C27: V1.3.11 | D27: Verify that the application sanitizes user input before passing to mail systems to protect against SMTP or IMAP injection. | E27: 2 | F27: Compliant | G27: Automatically marked compliant from passing evidence: input shape/range validation; unknown-field rejection; payload/request limit coverage; SQL injection regression and taint checks; SQL injection abuse-case regression. | H27: SR-28; SR-29; SR-30; SR-09; AC-05; ControllerIntegrationTests; SystemFunctionalTests; ControllerUnitTests; GlobalExceptionHandlerTest; application.properties; AbuseCaseRegressionTest; IastIntegrationTest; Bean Validation and request-shape controls detected | I27: Automatically inferred as implemented or justified from passing tests, source code, configuration, or build artifacts. | J27: Automated repository evidence | K27: ControllerIntegrationTests; SystemFunctionalTests; ControllerUnitTests; GlobalExceptionHandlerTest; application.properties; AbuseCaseRegressionTest; IastIntegrationTest; Bean Validation and request-shape controls detected | L27: input shape/range validation; unknown-field rejection; payload/request limit coverage; SQL injection regression and taint checks; SQL injection abuse-case regression | M27: Keep make asvs-tracker passing; reassess if code, tests, or scope changes.
A28: V1.3 | B28: Sanitization | C28: V1.3.12 | D28: Verify that regular expressions are free from elements causing exponential backtracking, and ensure untrusted input is sanitized to mitigate ReDoS or Runaway Regex attacks. | E28: 3 | F28: Compliant | G28: Automatically marked compliant from passing evidence: path traversal and report sandboxing; input shape/range validation; unknown-field rejection; payload/request limit coverage. | H28: SR-26; SR-28; SR-29; SR-30; PathValidatorImplTest; ReportDirectoryServiceImplTest; AbuseCaseRegressionTest; ControllerIntegrationTests; SystemFunctionalTests; ControllerUnitTests; GlobalExceptionHandlerTest; application.properties; Bean Validation and request-shape controls detected; path validation and report sandbox code detected | I28: Automatically inferred as implemented or justified from passing tests, source code, configuration, or build artifacts. | J28: Automated repository evidence | K28: PathValidatorImplTest; ReportDirectoryServiceImplTest; AbuseCaseRegressionTest; ControllerIntegrationTests; SystemFunctionalTests; ControllerUnitTests; GlobalExceptionHandlerTest; application.properties; Bean Validation and request-shape controls detected; path validation and report sandbox code detected | L28: path traversal and report sandboxing; input shape/range validation; unknown-field rejection; payload/request limit coverage | M28: Keep make asvs-tracker passing; reassess if code, tests, or scope changes.
A29: V1.4 | B29: Memory, String, and Unmanaged Code
A30: V1.4 | B30: Memory, String, and Unmanaged Code | C30: V1.4.1 | D30: Verify that the application uses memory-safe string, safer memory copy and pointer arithmetic to detect or prevent stack, buffer, or heap overflows. | E30: 2 | F30: N/A | G30: Automatically marked out of scope: This is a managed JVM application without native pointer arithmetic or application-managed memory allocation. | H30: Automated scope inference | I30: Out of scope for VendNet as currently implemented, or the requirement does not apply to this REST API/backend. | J30: Scope inference | K30: Not required for current backend scope. | L30: This is a managed JVM application without native pointer arithmetic or application-managed memory allocation. | M30: Revisit if the application scope changes.
A31: V1.4 | B31: Memory, String, and Unmanaged Code | C31: V1.4.2 | D31: Verify that sign, range, and input validation techniques are used to prevent integer overflows. | E31: 2 | F31: Compliant | G31: Automatically marked compliant from passing evidence: stock limit validation; input shape/range validation; unknown-field rejection; payload/request limit coverage. | H31: SR-25; SR-28; SR-29; SR-30; SlotServiceTest; SaleServiceTest; ControllerIntegrationTests; SystemFunctionalTests; ControllerUnitTests; GlobalExceptionHandlerTest; application.properties; Bean Validation and request-shape controls detected | I31: Automatically inferred as implemented or justified from passing tests, source code, configuration, or build artifacts. | J31: Automated repository evidence | K31: SlotServiceTest; SaleServiceTest; ControllerIntegrationTests; SystemFunctionalTests; ControllerUnitTests; GlobalExceptionHandlerTest; application.properties; Bean Validation and request-shape controls detected | L31: stock limit validation; input shape/range validation; unknown-field rejection; payload/request limit coverage | M31: Keep make asvs-tracker passing; reassess if code, tests, or scope changes.
A32: V1.4 | B32: Memory, String, and Unmanaged Code | C32: V1.4.3 | D32: Verify that dynamically allocated memory and resources are released, and that references or pointers to freed memory are removed or set to null to prevent dangling pointers and use-after-free vulnerabilities. | E32: 2 | F32: N/A | G32: Automatically marked out of scope: This is a managed JVM application without native pointer arithmetic or application-managed memory allocation. | H32: Automated scope inference | I32: Out of scope for VendNet as currently implemented, or the requirement does not apply to this REST API/backend. | J32: Scope inference | K32: Not required for current backend scope. | L32: This is a managed JVM application without native pointer arithmetic or application-managed memory allocation. | M32: Revisit if the application scope changes.
A33: V1.5 | B33: Safe Deserialization
A34: V1.5 | B34: Safe Deserialization | C34: V1.5.1 | D34: Verify that the application configures XML parsers to use a restrictive configuration and that unsafe features such as resolving external entities are disabled to prevent XML eXternal Entity (XXE) attacks. | E34: 1 | F34: N/A | G34: Automatically marked out of scope: No XML/SOAP API surface is present; controllers return JSON REST responses. | H34: Automated scope inference | I34: Out of scope for VendNet as currently implemented, or the requirement does not apply to this REST API/backend. | J34: Scope inference | K34: Not required for current backend scope. | L34: No XML/SOAP API surface is present; controllers return JSON REST responses. | M34: Revisit if the application scope changes.
A35: V1.5 | B35: Safe Deserialization | C35: V1.5.2 | D35: Verify that deserialization of untrusted data enforces safe input handling, such as using an allowlist of object types or restricting client-defined object types, to prevent deserialization attacks. Deserialization mechanisms that are explicitly defined as insecure must not be used with untrusted input. | E35: 2 | F35: Compliant | G35: Automatically marked compliant from passing evidence: input shape/range validation; unknown-field rejection; payload/request limit coverage. | H35: SR-28; SR-29; SR-30; ControllerIntegrationTests; SystemFunctionalTests; ControllerUnitTests; GlobalExceptionHandlerTest; application.properties; Bean Validation and request-shape controls detected | I35: Automatically inferred as implemented or justified from passing tests, source code, configuration, or build artifacts. | J35: Automated repository evidence | K35: ControllerIntegrationTests; SystemFunctionalTests; ControllerUnitTests; GlobalExceptionHandlerTest; application.properties; Bean Validation and request-shape controls detected | L35: input shape/range validation; unknown-field rejection; payload/request limit coverage | M35: Keep make asvs-tracker passing; reassess if code, tests, or scope changes.
A36: V1.5 | B36: Safe Deserialization | C36: V1.5.3 | D36: Verify that different parsers used in the application for the same data type (e.g., JSON parsers, XML parsers, URL parsers), perform parsing in a consistent way and use the same character encoding mechanism to avoid issues such as JSON Interoperability vulnerabilities or different URI or file parsing behavior being exploited in Remote File Inclusion (RFI) or Server-side Request Forgery (SSRF) attacks. | E36: 3 | F36: N/A | G36: Automatically marked out of scope: No XML/SOAP API surface is present; controllers return JSON REST responses. | H36: Automated scope inference | I36: Out of scope for VendNet as currently implemented, or the requirement does not apply to this REST API/backend. | J36: Scope inference | K36: Not required for current backend scope. | L36: No XML/SOAP API surface is present; controllers return JSON REST responses. | M36: Revisit if the application scope changes.

Sheet V2 - Validation and Business Lo
A1: Section ID | B1: Section Name | C1: Req ID | D1: Description | E1: Level | F1: Status | G1: Observations | H1: Reference / Link | I1: DX Status Meaning | J1: Evidence Type | K1: Automated Evidence | L1: Evidence Source | M1: Next Action
A2: V2.1 | B2: Validation and Business Logic Documentation
A3: V2.1 | B3: Validation and Business Logic Documentation | C3: V2.1.1 | D3: Verify that the application's documentation defines input validation rules for how to check the validity of data items against an expected structure. This could be common data formats such as credit card numbers, email addresses, telephone numbers, or it could be an internal data format. | E3: 1 | F3: Compliant | G3: Automatically marked compliant from passing evidence: server-side price enforcement; pagination/large-response controls; input shape/range validation; unknown-field rejection; payload/request limit coverage. | H3: SR-24; SR-31; SR-28; SR-29; SR-30; SaleServiceTest; AbuseCaseRegressionTest; ControllerIntegrationTests; SystemFunctionalTests; ControllerUnitTests; GlobalExceptionHandlerTest; application.properties; Bean Validation and request-shape controls detected | I3: Automatically inferred as implemented or justified from passing tests, source code, configuration, or build artifacts. | J3: Automated repository evidence | K3: SaleServiceTest; AbuseCaseRegressionTest; ControllerIntegrationTests; SystemFunctionalTests; ControllerUnitTests; GlobalExceptionHandlerTest; application.properties; Bean Validation and request-shape controls detected | L3: server-side price enforcement; pagination/large-response controls; input shape/range validation; unknown-field rejection; payload/request limit coverage | M3: Keep make asvs-tracker passing; reassess if code, tests, or scope changes.
A4: V2.1 | B4: Validation and Business Logic Documentation | C4: V2.1.2 | D4: Verify that the application's documentation defines how to validate the logical and contextual consistency of combined data items, such as checking that suburb and ZIP code match. | E4: 2 | F4: Compliant | G4: Automatically marked compliant from passing evidence: stock limit validation; input shape/range validation; unknown-field rejection; payload/request limit coverage; authentication audit logging; sensitive log data checks; safe error response checks. | H4: SR-25; SR-28; SR-29; SR-30; SR-37; SR-45; SR-46; SlotServiceTest; SaleServiceTest; ControllerIntegrationTests; SystemFunctionalTests; ControllerUnitTests; GlobalExceptionHandlerTest; application.properties; AuthServiceTest; AuditLoggerTest; Bean Validation and request-shape controls detected; audit logging implementation detected; centralized safe error handling detected | I4: Automatically inferred as implemented or justified from passing tests, source code, configuration, or build artifacts. | J4: Automated repository evidence | K4: SlotServiceTest; SaleServiceTest; ControllerIntegrationTests; SystemFunctionalTests; ControllerUnitTests; GlobalExceptionHandlerTest; application.properties; AuthServiceTest; AuditLoggerTest; Bean Validation and request-shape controls detected; audit logging implementation detected; centralized safe error handling detected | L4: stock limit validation; input shape/range validation; unknown-field rejection; payload/request limit coverage; authentication audit logging; sensitive log data checks; safe error response checks | M4: Keep make asvs-tracker passing; reassess if code, tests, or scope changes.
A5: V2.1 | B5: Validation and Business Logic Documentation | C5: V2.1.3 | D5: Verify that expectations for business logic limits and validations are documented, including both per-user and globally across the application. | E5: 2 | F5: Compliant | G5: Automatically marked compliant from passing evidence: administrator MFA; safe error response checks; input shape/range validation; unknown-field rejection; payload/request limit coverage; transaction and stock consistency; server-side price enforcement; stock limit validation; client-supplied price abuse-case regression; TOCTOU/stock race abuse-case regression; authentication audit logging; sensitive log data checks. | H5: NFR-01; NFR-15; SR-01; SR-46; SR-28; SR-29; SR-30; SR-15; SR-24; SR-25; AC-03; AC-07; SR-37; SR-45; AuthServiceTest; AuthControllerIntegrationTest; GlobalExceptionHandlerTest; ControllerIntegrationTests; SystemFunctionalTests; ControllerUnitTests; application.properties; SaleServiceTest; SlotServiceTest; AbuseCaseRegressionTest; AuditLoggerTest; MFA/TOTP code and tests detected; Bean Validation and request-shape controls detected; audit logging implementation detected; centralized safe error handling detected | I5: Automatically inferred as implemented or justified from passing tests, source code, configuration, or build artifacts. | J5: Automated repository evidence | K5: AuthServiceTest; AuthControllerIntegrationTest; GlobalExceptionHandlerTest; ControllerIntegrationTests; SystemFunctionalTests; ControllerUnitTests; application.properties; SaleServiceTest; SlotServiceTest; AbuseCaseRegressionTest; AuditLoggerTest; MFA/TOTP code and tests detected; Bean Validation and request-shape controls detected; audit logging implementation detected; centralized safe error handling detected | L5: administrator MFA; safe error response checks; input shape/range validation; unknown-field rejection; payload/request limit coverage; transaction and stock consistency; server-side price enforcement; stock limit validation; client-supplied price abuse-case regression; TOCTOU/stock race abuse-case regression; authentication audit logging; sensitive log data checks | M5: Keep make asvs-tracker passing; reassess if code, tests, or scope changes.
A6: V2.2 | B6: Input Validation
A7: V2.2 | B7: Input Validation | C7: V2.2.1 | D7: Verify that input is validated to enforce business or functional expectations for that input. This should either use positive validation against an allow list of values, patterns, and ranges, or be based on comparing the input to an expected structure and logical limits according to predefined rules. For L1, this can focus on input which is used to make specific business or security decisions. For L2 and up, this should apply to all input. | E7: 1 | F7: Compliant | G7: Automatically marked compliant from passing evidence: server-side price enforcement; stock limit validation; path traversal and report sandboxing; input shape/range validation; unknown-field rejection; payload/request limit coverage; pagination/large-response controls; authentication audit logging; sensitive log data checks; safe error response checks. | H7: SR-24; SR-25; SR-26; SR-28; SR-29; SR-30; SR-31; SR-37; SR-45; SR-46; SaleServiceTest; AbuseCaseRegressionTest; SlotServiceTest; PathValidatorImplTest; ReportDirectoryServiceImplTest; ControllerIntegrationTests; SystemFunctionalTests; ControllerUnitTests; GlobalExceptionHandlerTest; application.properties; AuthServiceTest; AuditLoggerTest; Bean Validation and request-shape controls detected; path validation and report sandbox code detected; audit logging implementation detected; centralized safe error handling detected | I7: Automatically inferred as implemented or justified from passing tests, source code, configuration, or build artifacts. | J7: Automated repository evidence | K7: SaleServiceTest; AbuseCaseRegressionTest; SlotServiceTest; PathValidatorImplTest; ReportDirectoryServiceImplTest; ControllerIntegrationTests; SystemFunctionalTests; ControllerUnitTests; GlobalExceptionHandlerTest; application.properties; AuthServiceTest; AuditLoggerTest; Bean Validation and request-shape controls detected; path validation and report sandbox code detected; audit logging implementation detected; centralized safe error handling detected | L7: server-side price enforcement; stock limit validation; path traversal and report sandboxing; input shape/range validation; unknown-field rejection; payload/request limit coverage; pagination/large-response controls; authentication audit logging; sensitive log data checks; safe error response checks | M7: Keep make asvs-tracker passing; reassess if code, tests, or scope changes.
A8: V2.2 | B8: Input Validation | C8: V2.2.2 | D8: Verify that the application is designed to enforce input validation at a trusted service layer. While client-side validation improves usability and should be encouraged, it must not be relied upon as a security control. | E8: 1 | F8: Compliant | G8: Automatically marked compliant from passing evidence: server-side price enforcement; stock limit validation; input shape/range validation; unknown-field rejection; payload/request limit coverage. | H8: SR-24; SR-25; SR-28; SR-29; SR-30; SaleServiceTest; AbuseCaseRegressionTest; SlotServiceTest; ControllerIntegrationTests; SystemFunctionalTests; ControllerUnitTests; GlobalExceptionHandlerTest; application.properties; Bean Validation and request-shape controls detected | I8: Automatically inferred as implemented or justified from passing tests, source code, configuration, or build artifacts. | J8: Automated repository evidence | K8: SaleServiceTest; AbuseCaseRegressionTest; SlotServiceTest; ControllerIntegrationTests; SystemFunctionalTests; ControllerUnitTests; GlobalExceptionHandlerTest; application.properties; Bean Validation and request-shape controls detected | L8: server-side price enforcement; stock limit validation; input shape/range validation; unknown-field rejection; payload/request limit coverage | M8: Keep make asvs-tracker passing; reassess if code, tests, or scope changes.
A9: V2.2 | B9: Input Validation | C9: V2.2.3 | D9: Verify that the application ensures that combinations of related data items are reasonable according to the pre-defined rules. | E9: 2 | F9: Compliant | G9: Automatically marked compliant from passing evidence: transaction and stock consistency; stock limit validation; input shape/range validation; unknown-field rejection; payload/request limit coverage. | H9: SR-15; SR-25; SR-28; SR-29; SR-30; SaleServiceTest; SlotServiceTest; AbuseCaseRegressionTest; ControllerIntegrationTests; SystemFunctionalTests; ControllerUnitTests; GlobalExceptionHandlerTest; application.properties; Bean Validation and request-shape controls detected | I9: Automatically inferred as implemented or justified from passing tests, source code, configuration, or build artifacts. | J9: Automated repository evidence | K9: SaleServiceTest; SlotServiceTest; AbuseCaseRegressionTest; ControllerIntegrationTests; SystemFunctionalTests; ControllerUnitTests; GlobalExceptionHandlerTest; application.properties; Bean Validation and request-shape controls detected | L9: transaction and stock consistency; stock limit validation; input shape/range validation; unknown-field rejection; payload/request limit coverage | M9: Keep make asvs-tracker passing; reassess if code, tests, or scope changes.
A10: V2.3 | B10: Business Logic Security
A11: V2.3 | B11: Business Logic Security | C11: V2.3.1 | D11: Verify that the application will only process business logic flows for the same user in the expected sequential step order and without skipping steps. | E11: 1 | F11: Compliant | G11: Automatically marked compliant from passing evidence: input shape/range validation; unknown-field rejection; payload/request limit coverage; transaction and stock consistency; server-side price enforcement; stock limit validation; client-supplied price abuse-case regression; TOCTOU/stock race abuse-case regression; authentication audit logging; sensitive log data checks; safe error response checks. | H11: SR-28; SR-29; SR-30; SR-15; SR-24; SR-25; AC-03; AC-07; SR-37; SR-45; SR-46; ControllerIntegrationTests; SystemFunctionalTests; ControllerUnitTests; GlobalExceptionHandlerTest; application.properties; SaleServiceTest; SlotServiceTest; AbuseCaseRegressionTest; AuthServiceTest; AuditLoggerTest; Bean Validation and request-shape controls detected; audit logging implementation detected; centralized safe error handling detected | I11: Automatically inferred as implemented or justified from passing tests, source code, configuration, or build artifacts. | J11: Automated repository evidence | K11: ControllerIntegrationTests; SystemFunctionalTests; ControllerUnitTests; GlobalExceptionHandlerTest; application.properties; SaleServiceTest; SlotServiceTest; AbuseCaseRegressionTest; AuthServiceTest; AuditLoggerTest; Bean Validation and request-shape controls detected; audit logging implementation detected; centralized safe error handling detected | L11: input shape/range validation; unknown-field rejection; payload/request limit coverage; transaction and stock consistency; server-side price enforcement; stock limit validation; client-supplied price abuse-case regression; TOCTOU/stock race abuse-case regression; authentication audit logging; sensitive log data checks; safe error response checks | M11: Keep make asvs-tracker passing; reassess if code, tests, or scope changes.
A12: V2.3 | B12: Business Logic Security | C12: V2.3.2 | D12: Verify that business logic limits are implemented per the application's documentation to avoid business logic flaws being exploited. | E12: 2 | F12: Compliant | G12: Automatically marked compliant from passing evidence: server-side price enforcement; stock limit validation; input shape/range validation; unknown-field rejection; payload/request limit coverage; transaction and stock consistency; client-supplied price abuse-case regression; TOCTOU/stock race abuse-case regression; authentication audit logging; sensitive log data checks; safe error response checks. | H12: SR-24; SR-25; SR-28; SR-29; SR-30; SR-15; AC-03; AC-07; SR-37; SR-45; SR-46; SaleServiceTest; AbuseCaseRegressionTest; SlotServiceTest; ControllerIntegrationTests; SystemFunctionalTests; ControllerUnitTests; GlobalExceptionHandlerTest; application.properties; AuthServiceTest; AuditLoggerTest; Bean Validation and request-shape controls detected; audit logging implementation detected; centralized safe error handling detected | I12: Automatically inferred as implemented or justified from passing tests, source code, configuration, or build artifacts. | J12: Automated repository evidence | K12: SaleServiceTest; AbuseCaseRegressionTest; SlotServiceTest; ControllerIntegrationTests; SystemFunctionalTests; ControllerUnitTests; GlobalExceptionHandlerTest; application.properties; AuthServiceTest; AuditLoggerTest; Bean Validation and request-shape controls detected; audit logging implementation detected; centralized safe error handling detected | L12: server-side price enforcement; stock limit validation; input shape/range validation; unknown-field rejection; payload/request limit coverage; transaction and stock consistency; client-supplied price abuse-case regression; TOCTOU/stock race abuse-case regression; authentication audit logging; sensitive log data checks; safe error response checks | M12: Keep make asvs-tracker passing; reassess if code, tests, or scope changes.
A13: V2.3 | B13: Business Logic Security | C13: V2.3.3 | D13: Verify that transactions are being used at the business logic level such that either a business logic operation succeeds in its entirety or it is rolled back to the previous correct state. | E13: 2 | F13: Compliant | G13: Automatically marked compliant from passing evidence: transaction and stock consistency; input shape/range validation; unknown-field rejection; payload/request limit coverage; server-side price enforcement; stock limit validation; client-supplied price abuse-case regression; TOCTOU/stock race abuse-case regression; authentication audit logging; sensitive log data checks; safe error response checks. | H13: NFR-08; SR-15; SR-28; SR-29; SR-30; SR-24; SR-25; AC-03; AC-07; SR-37; SR-45; SR-46; SaleServiceTest; SlotServiceTest; AbuseCaseRegressionTest; ControllerIntegrationTests; SystemFunctionalTests; ControllerUnitTests; GlobalExceptionHandlerTest; application.properties; AuthServiceTest; AuditLoggerTest; Bean Validation and request-shape controls detected; audit logging implementation detected; centralized safe error handling detected | I13: Automatically inferred as implemented or justified from passing tests, source code, configuration, or build artifacts. | J13: Automated repository evidence | K13: SaleServiceTest; SlotServiceTest; AbuseCaseRegressionTest; ControllerIntegrationTests; SystemFunctionalTests; ControllerUnitTests; GlobalExceptionHandlerTest; application.properties; AuthServiceTest; AuditLoggerTest; Bean Validation and request-shape controls detected; audit logging implementation detected; centralized safe error handling detected | L13: transaction and stock consistency; input shape/range validation; unknown-field rejection; payload/request limit coverage; server-side price enforcement; stock limit validation; client-supplied price abuse-case regression; TOCTOU/stock race abuse-case regression; authentication audit logging; sensitive log data checks; safe error response checks | M13: Keep make asvs-tracker passing; reassess if code, tests, or scope changes.
A14: V2.3 | B14: Business Logic Security | C14: V2.3.4 | D14: Verify that business logic level locking mechanisms are used to ensure that limited quantity resources (such as theater seats or delivery slots) cannot be double-booked by manipulating the application's logic. | E14: 2 | F14: Compliant | G14: Automatically marked compliant from passing evidence: transaction and stock consistency; input shape/range validation; unknown-field rejection; payload/request limit coverage; server-side price enforcement; stock limit validation; client-supplied price abuse-case regression; TOCTOU/stock race abuse-case regression; authentication audit logging; sensitive log data checks; safe error response checks. | H14: SR-15; SR-28; SR-29; SR-30; SR-24; SR-25; AC-03; AC-07; SR-37; SR-45; SR-46; SaleServiceTest; SlotServiceTest; AbuseCaseRegressionTest; ControllerIntegrationTests; SystemFunctionalTests; ControllerUnitTests; GlobalExceptionHandlerTest; application.properties; AuthServiceTest; AuditLoggerTest; Bean Validation and request-shape controls detected; audit logging implementation detected; centralized safe error handling detected | I14: Automatically inferred as implemented or justified from passing tests, source code, configuration, or build artifacts. | J14: Automated repository evidence | K14: SaleServiceTest; SlotServiceTest; AbuseCaseRegressionTest; ControllerIntegrationTests; SystemFunctionalTests; ControllerUnitTests; GlobalExceptionHandlerTest; application.properties; AuthServiceTest; AuditLoggerTest; Bean Validation and request-shape controls detected; audit logging implementation detected; centralized safe error handling detected | L14: transaction and stock consistency; input shape/range validation; unknown-field rejection; payload/request limit coverage; server-side price enforcement; stock limit validation; client-supplied price abuse-case regression; TOCTOU/stock race abuse-case regression; authentication audit logging; sensitive log data checks; safe error response checks | M14: Keep make asvs-tracker passing; reassess if code, tests, or scope changes.
A15: V2.3 | B15: Business Logic Security | C15: V2.3.5 | D15: Verify that high-value business logic flows require multi-user approval to prevent unauthorized or accidental actions. This could include but is not limited to large monetary transfers, contract approvals, access to classified information, or safety overrides in manufacturing. | E15: 3 | F15: Compliant | G15: Automatically marked compliant from passing evidence: input shape/range validation; unknown-field rejection; payload/request limit coverage; transaction and stock consistency; server-side price enforcement; stock limit validation; client-supplied price abuse-case regression; TOCTOU/stock race abuse-case regression; authentication audit logging; sensitive log data checks; safe error response checks. | H15: SR-28; SR-29; SR-30; SR-15; SR-24; SR-25; AC-03; AC-07; SR-37; SR-45; SR-46; ControllerIntegrationTests; SystemFunctionalTests; ControllerUnitTests; GlobalExceptionHandlerTest; application.properties; SaleServiceTest; SlotServiceTest; AbuseCaseRegressionTest; AuthServiceTest; AuditLoggerTest; Bean Validation and request-shape controls detected; audit logging implementation detected; centralized safe error handling detected | I15: Automatically inferred as implemented or justified from passing tests, source code, configuration, or build artifacts. | J15: Automated repository evidence | K15: ControllerIntegrationTests; SystemFunctionalTests; ControllerUnitTests; GlobalExceptionHandlerTest; application.properties; SaleServiceTest; SlotServiceTest; AbuseCaseRegressionTest; AuthServiceTest; AuditLoggerTest; Bean Validation and request-shape controls detected; audit logging implementation detected; centralized safe error handling detected | L15: input shape/range validation; unknown-field rejection; payload/request limit coverage; transaction and stock consistency; server-side price enforcement; stock limit validation; client-supplied price abuse-case regression; TOCTOU/stock race abuse-case regression; authentication audit logging; sensitive log data checks; safe error response checks | M15: Keep make asvs-tracker passing; reassess if code, tests, or scope changes.
A16: V2.4 | B16: Anti-automation
A17: V2.4 | B17: Anti-automation | C17: V2.4.1 | D17: Verify that anti-automation controls are in place to protect against excessive calls to application functions that could lead to data exfiltration, garbage-data creation, quota exhaustion, rate-limit breaches, denial-of-service, or overuse of costly resources. | E17: 2 | F17: Compliant | G17: Automatically marked compliant from passing evidence: failed-login lockout behaviour; payload/request limit coverage; pagination/large-response controls; input shape/range validation; unknown-field rejection. | H17: SR-07; SR-30; SR-31; SR-28; SR-29; AuthServiceTest; AuthControllerIntegrationTest; SystemFunctionalTests; application.properties; ControllerIntegrationTests; ControllerUnitTests; GlobalExceptionHandlerTest; Bean Validation and request-shape controls detected | I17: Automatically inferred as implemented or justified from passing tests, source code, configuration, or build artifacts. | J17: Automated repository evidence | K17: AuthServiceTest; AuthControllerIntegrationTest; SystemFunctionalTests; application.properties; ControllerIntegrationTests; ControllerUnitTests; GlobalExceptionHandlerTest; Bean Validation and request-shape controls detected | L17: failed-login lockout behaviour; payload/request limit coverage; pagination/large-response controls; input shape/range validation; unknown-field rejection | M17: Keep make asvs-tracker passing; reassess if code, tests, or scope changes.
A18: V2.4 | B18: Anti-automation | C18: V2.4.2 | D18: Verify that business logic flows require realistic human timing, preventing excessively rapid transaction submissions. | E18: 3 | F18: Compliant | G18: Automatically marked compliant from passing evidence: administrator MFA; user data access isolation; input shape/range validation; unknown-field rejection; payload/request limit coverage; transaction and stock consistency; server-side price enforcement; stock limit validation; client-supplied price abuse-case regression; TOCTOU/stock race abuse-case regression; authentication audit logging; sensitive log data checks; safe error response checks. | H18: SR-01; SR-08; SR-28; SR-29; SR-30; SR-15; SR-24; SR-25; AC-03; AC-07; SR-37; SR-45; SR-46; AuthServiceTest; AuthControllerIntegrationTest; RbacIntegrationTest; SystemFunctionalTests; ControllerIntegrationTests; ControllerUnitTests; GlobalExceptionHandlerTest; application.properties; SaleServiceTest; SlotServiceTest; AbuseCaseRegressionTest; AuditLoggerTest; MFA/TOTP code and tests detected; Spring method security and RBAC annotations detected; Bean Validation and request-shape controls detected; audit logging implementation detected; centralized safe error handling detected | I18: Automatically inferred as implemented or justified from passing tests, source code, configuration, or build artifacts. | J18: Automated repository evidence | K18: AuthServiceTest; AuthControllerIntegrationTest; RbacIntegrationTest; SystemFunctionalTests; ControllerIntegrationTests; ControllerUnitTests; GlobalExceptionHandlerTest; application.properties; SaleServiceTest; SlotServiceTest; AbuseCaseRegressionTest; AuditLoggerTest; MFA/TOTP code and tests detected; Spring method security and RBAC annotations detected; Bean Validation and request-shape controls detected; audit logging implementation detected; centralized safe error handling detected | L18: administrator MFA; user data access isolation; input shape/range validation; unknown-field rejection; payload/request limit coverage; transaction and stock consistency; server-side price enforcement; stock limit validation; client-supplied price abuse-case regression; TOCTOU/stock race abuse-case regression; authentication audit logging; sensitive log data checks; safe error response checks | M18: Keep make asvs-tracker passing; reassess if code, tests, or scope changes.

Sheet V3 - Web Frontend Security
A1: Section ID | B1: Section Name | C1: Req ID | D1: Description | E1: Level | F1: Status | G1: Observations | H1: Reference / Link | I1: DX Status Meaning | J1: Evidence Type | K1: Automated Evidence | L1: Evidence Source | M1: Next Action
A2: V3.1 | B2: Web Frontend Security Documentation
A3: V3.1 | B3: Web Frontend Security Documentation | C3: V3.1.1 | D3: Verify that application documentation states the expected security features that browsers using the application must support (such as HTTPS, HTTP Strict Transport Security (HSTS), Content Security Policy (CSP), and other relevant HTTP security mechanisms). It must also define how the application must behave when some of these features are not available (such as warning the user or blocking access). | E3: 3 | F3: N/A | G3: Automatically marked out of scope: VendNet is a Spring REST API/backend in this repository; no browser frontend or DOM-rendering surface is present. | H3: Automated scope inference | I3: Out of scope for VendNet as currently implemented, or the requirement does not apply to this REST API/backend. | J3: Scope inference | K3: Not required for current backend scope. | L3: VendNet is a Spring REST API/backend in this repository; no browser frontend or DOM-rendering surface is present. | M3: Revisit if the application scope changes.
A4: V3.2 | B4: Unintended Content Interpretation
A5: V3.2 | B5: Unintended Content Interpretation | C5: V3.2.1 | D5: Verify that security controls are in place to prevent browsers from rendering content or functionality in HTTP responses in an incorrect context (e.g., when an API, a user-uploaded file or other resource is requested directly). Possible controls could include: not serving the content unless HTTP request header fields (such as Sec-Fetch-\*) indicate it is the correct context, using the sandbox directive of the Content-Security-Policy header field or using the attachment disposition type in the Content-Disposition header field. | E5: 1 | F5: N/A | G5: Automatically marked out of scope: VendNet is a Spring REST API/backend in this repository; no browser frontend or DOM-rendering surface is present. | H5: Automated scope inference | I5: Out of scope for VendNet as currently implemented, or the requirement does not apply to this REST API/backend. | J5: Scope inference | K5: Not required for current backend scope. | L5: VendNet is a Spring REST API/backend in this repository; no browser frontend or DOM-rendering surface is present. | M5: Revisit if the application scope changes.
A6: V3.2 | B6: Unintended Content Interpretation | C6: V3.2.2 | D6: Verify that content intended to be displayed as text, rather than rendered as HTML, is handled using safe rendering functions (such as createTextNode or textContent) to prevent unintended execution of content such as HTML or JavaScript. | E6: 1 | F6: N/A | G6: Automatically marked out of scope: VendNet is a Spring REST API/backend in this repository; no browser frontend or DOM-rendering surface is present. | H6: Automated scope inference | I6: Out of scope for VendNet as currently implemented, or the requirement does not apply to this REST API/backend. | J6: Scope inference | K6: Not required for current backend scope. | L6: VendNet is a Spring REST API/backend in this repository; no browser frontend or DOM-rendering surface is present. | M6: Revisit if the application scope changes.
A7: V3.2 | B7: Unintended Content Interpretation | C7: V3.2.3 | D7: Verify that the application avoids DOM clobbering when using client-side JavaScript by employing explicit variable declarations, performing strict type checking, avoiding storing global variables on the document object, and implementing namespace isolation. | E7: 3 | F7: N/A | G7: Automatically marked out of scope: VendNet is a Spring REST API/backend in this repository; no browser frontend or DOM-rendering surface is present. | H7: Automated scope inference | I7: Out of scope for VendNet as currently implemented, or the requirement does not apply to this REST API/backend. | J7: Scope inference | K7: Not required for current backend scope. | L7: VendNet is a Spring REST API/backend in this repository; no browser frontend or DOM-rendering surface is present. | M7: Revisit if the application scope changes.
A8: V3.3 | B8: Cookie Setup
A9: V3.3 | B9: Cookie Setup | C9: V3.3.1 | D9: Verify that cookies have the 'Secure' attribute set, and if the '\__Host-' prefix is not used for the cookie name, the '__Secure-' prefix must be used for the cookie name. | E9: 1 | F9: N/A | G9: Automatically marked out of scope: VendNet is a Spring REST API/backend in this repository; no browser frontend or DOM-rendering surface is present. | H9: Automated scope inference | I9: Out of scope for VendNet as currently implemented, or the requirement does not apply to this REST API/backend. | J9: Scope inference | K9: Not required for current backend scope. | L9: VendNet is a Spring REST API/backend in this repository; no browser frontend or DOM-rendering surface is present. | M9: Revisit if the application scope changes.
A10: V3.3 | B10: Cookie Setup | C10: V3.3.2 | D10: Verify that each cookie's 'SameSite' attribute value is set according to the purpose of the cookie, to limit exposure to user interface redress attacks and browser-based request forgery attacks, commonly known as cross-site request forgery (CSRF). | E10: 2 | F10: N/A | G10: Automatically marked out of scope: VendNet is a Spring REST API/backend in this repository; no browser frontend or DOM-rendering surface is present. | H10: Automated scope inference | I10: Out of scope for VendNet as currently implemented, or the requirement does not apply to this REST API/backend. | J10: Scope inference | K10: Not required for current backend scope. | L10: VendNet is a Spring REST API/backend in this repository; no browser frontend or DOM-rendering surface is present. | M10: Revisit if the application scope changes.
A11: V3.3 | B11: Cookie Setup | C11: V3.3.3 | D11: Verify that cookies have the '__Host-' prefix for the cookie name unless they are explicitly designed to be shared with other hosts. | E11: 2 | F11: N/A | G11: Automatically marked out of scope: VendNet is a Spring REST API/backend in this repository; no browser frontend or DOM-rendering surface is present. | H11: Automated scope inference | I11: Out of scope for VendNet as currently implemented, or the requirement does not apply to this REST API/backend. | J11: Scope inference | K11: Not required for current backend scope. | L11: VendNet is a Spring REST API/backend in this repository; no browser frontend or DOM-rendering surface is present. | M11: Revisit if the application scope changes.
A12: V3.3 | B12: Cookie Setup | C12: V3.3.4 | D12: Verify that if the value of a cookie is not meant to be accessible to client-side scripts (such as a session token), the cookie must have the 'HttpOnly' attribute set and the same value (e. g. session token) must only be transferred to the client via the 'Set-Cookie' header field. | E12: 2 | F12: N/A | G12: Automatically marked out of scope: VendNet is a Spring REST API/backend in this repository; no browser frontend or DOM-rendering surface is present. | H12: Automated scope inference | I12: Out of scope for VendNet as currently implemented, or the requirement does not apply to this REST API/backend. | J12: Scope inference | K12: Not required for current backend scope. | L12: VendNet is a Spring REST API/backend in this repository; no browser frontend or DOM-rendering surface is present. | M12: Revisit if the application scope changes.
A13: V3.3 | B13: Cookie Setup | C13: V3.3.5 | D13: Verify that when the application writes a cookie, the cookie name and value length combined are not over 4096 bytes. Overly large cookies will not be stored by the browser and therefore not sent with requests, preventing the user from using application functionality which relies on that cookie. | E13: 3 | F13: N/A | G13: Automatically marked out of scope: VendNet is a Spring REST API/backend in this repository; no browser frontend or DOM-rendering surface is present. | H13: Automated scope inference | I13: Out of scope for VendNet as currently implemented, or the requirement does not apply to this REST API/backend. | J13: Scope inference | K13: Not required for current backend scope. | L13: VendNet is a Spring REST API/backend in this repository; no browser frontend or DOM-rendering surface is present. | M13: Revisit if the application scope changes.
A14: V3.4 | B14: Browser Security Mechanism Headers
A15: V3.4 | B15: Browser Security Mechanism Headers | C15: V3.4.1 | D15: Verify that a Strict-Transport-Security header field is included on all responses to enforce an HTTP Strict Transport Security (HSTS) policy. A maximum age of at least 1 year must be defined, and for L2 and up, the policy must apply to all subdomains as well. | E15: 1 | F15: N/A | G15: Automatically marked out of scope: VendNet is a Spring REST API/backend in this repository; no browser frontend or DOM-rendering surface is present. | H15: Automated scope inference | I15: Out of scope for VendNet as currently implemented, or the requirement does not apply to this REST API/backend. | J15: Scope inference | K15: Not required for current backend scope. | L15: VendNet is a Spring REST API/backend in this repository; no browser frontend or DOM-rendering surface is present. | M15: Revisit if the application scope changes.
A16: V3.4 | B16: Browser Security Mechanism Headers | C16: V3.4.2 | D16: Verify that the Cross-Origin Resource Sharing (CORS) Access-Control-Allow-Origin header field is a fixed value by the application, or if the Origin HTTP request header field value is used, it is validated against an allowlist of trusted origins. When 'Access-Control-Allow-Origin: *' needs to be used, verify that the response does not include any sensitive information. | E16: 1 | F16: N/A | G16: Automatically marked out of scope: VendNet is a Spring REST API/backend in this repository; no browser frontend or DOM-rendering surface is present. | H16: Automated scope inference | I16: Out of scope for VendNet as currently implemented, or the requirement does not apply to this REST API/backend. | J16: Scope inference | K16: Not required for current backend scope. | L16: VendNet is a Spring REST API/backend in this repository; no browser frontend or DOM-rendering surface is present. | M16: Revisit if the application scope changes.
A17: V3.4 | B17: Browser Security Mechanism Headers | C17: V3.4.3 | D17: Verify that HTTP responses include a Content-Security-Policy response header field which defines directives to ensure the browser only loads and executes trusted content or resources, in order to limit execution of malicious JavaScript. As a minimum, a global policy must be used which includes the directives object-src 'none' and base-uri 'none' and defines either an allowlist or uses nonces or hashes. For an L3 application, a per-response policy with nonces or hashes must be defined. | E17: 2 | F17: N/A | G17: Automatically marked out of scope: VendNet is a Spring REST API/backend in this repository; no browser frontend or DOM-rendering surface is present. | H17: Automated scope inference | I17: Out of scope for VendNet as currently implemented, or the requirement does not apply to this REST API/backend. | J17: Scope inference | K17: Not required for current backend scope. | L17: VendNet is a Spring REST API/backend in this repository; no browser frontend or DOM-rendering surface is present. | M17: Revisit if the application scope changes.
A18: V3.4 | B18: Browser Security Mechanism Headers | C18: V3.4.4 | D18: Verify that all HTTP responses contain an 'X-Content-Type-Options: nosniff' header field. This instructs browsers not to use content sniffing and MIME type guessing for the given response, and to require the response's Content-Type header field value to match the destination resource. For example, the response to a request for a style is only accepted if the response's Content-Type is 'text/css'. This also enables the use of the Cross-Origin Read Blocking (CORB) functionality by the browser. | E18: 2 | F18: N/A | G18: Automatically marked out of scope: VendNet is a Spring REST API/backend in this repository; no browser frontend or DOM-rendering surface is present. | H18: Automated scope inference | I18: Out of scope for VendNet as currently implemented, or the requirement does not apply to this REST API/backend. | J18: Scope inference | K18: Not required for current backend scope. | L18: VendNet is a Spring REST API/backend in this repository; no browser frontend or DOM-rendering surface is present. | M18: Revisit if the application scope changes.
A19: V3.4 | B19: Browser Security Mechanism Headers | C19: V3.4.5 | D19: Verify that the application sets a referrer policy to prevent leakage of technically sensitive data to third-party services via the 'Referer' HTTP request header field. This can be done using the Referrer-Policy HTTP response header field or via HTML element attributes. Sensitive data could include path and query data in the URL, and for internal non-public applications also the hostname. | E19: 2 | F19: N/A | G19: Automatically marked out of scope: VendNet is a Spring REST API/backend in this repository; no browser frontend or DOM-rendering surface is present. | H19: Automated scope inference | I19: Out of scope for VendNet as currently implemented, or the requirement does not apply to this REST API/backend. | J19: Scope inference | K19: Not required for current backend scope. | L19: VendNet is a Spring REST API/backend in this repository; no browser frontend or DOM-rendering surface is present. | M19: Revisit if the application scope changes.
A20: V3.4 | B20: Browser Security Mechanism Headers | C20: V3.4.6 | D20: Verify that the web application uses the frame-ancestors directive of the Content-Security-Policy header field for every HTTP response to ensure that it cannot be embedded by default and that embedding of specific resources is allowed only when necessary. Note that the X-Frame-Options header field, although supported by browsers, is obsolete and may not be relied upon. | E20: 2 | F20: N/A | G20: Automatically marked out of scope: VendNet is a Spring REST API/backend in this repository; no browser frontend or DOM-rendering surface is present. | H20: Automated scope inference | I20: Out of scope for VendNet as currently implemented, or the requirement does not apply to this REST API/backend. | J20: Scope inference | K20: Not required for current backend scope. | L20: VendNet is a Spring REST API/backend in this repository; no browser frontend or DOM-rendering surface is present. | M20: Revisit if the application scope changes.
A21: V3.4 | B21: Browser Security Mechanism Headers | C21: V3.4.7 | D21: Verify that the Content-Security-Policy header field specifies a location to report violations. | E21: 3 | F21: N/A | G21: Automatically marked out of scope: VendNet is a Spring REST API/backend in this repository; no browser frontend or DOM-rendering surface is present. | H21: Automated scope inference | I21: Out of scope for VendNet as currently implemented, or the requirement does not apply to this REST API/backend. | J21: Scope inference | K21: Not required for current backend scope. | L21: VendNet is a Spring REST API/backend in this repository; no browser frontend or DOM-rendering surface is present. | M21: Revisit if the application scope changes.
A22: V3.4 | B22: Browser Security Mechanism Headers | C22: V3.4.8 | D22: Verify that all HTTP responses that initiate a document rendering (such as responses with Content-Type text/html), include the Cross‑Origin‑Opener‑Policy header field with the same-origin directive or the same-origin-allow-popups directive as required. This prevents attacks that abuse shared access to Window objects, such as tabnabbing and frame counting. | E22: 3 | F22: N/A | G22: Automatically marked out of scope: VendNet is a Spring REST API/backend in this repository; no browser frontend or DOM-rendering surface is present. | H22: Automated scope inference | I22: Out of scope for VendNet as currently implemented, or the requirement does not apply to this REST API/backend. | J22: Scope inference | K22: Not required for current backend scope. | L22: VendNet is a Spring REST API/backend in this repository; no browser frontend or DOM-rendering surface is present. | M22: Revisit if the application scope changes.
A23: V3.5 | B23: Browser Origin Separation
A24: V3.5 | B24: Browser Origin Separation | C24: V3.5.1 | D24: Verify that, if the application does not rely on the CORS preflight mechanism to prevent disallowed cross-origin requests to use sensitive functionality, these requests are validated to ensure they originate from the application itself. This may be done by using and validating anti-forgery tokens or requiring extra HTTP header fields that are not CORS-safelisted request-header fields. This is to defend against browser-based request forgery attacks, commonly known as cross-site request forgery (CSRF). | E24: 1 | F24: N/A | G24: Automatically marked out of scope: VendNet is a Spring REST API/backend in this repository; no browser frontend or DOM-rendering surface is present. | H24: Automated scope inference | I24: Out of scope for VendNet as currently implemented, or the requirement does not apply to this REST API/backend. | J24: Scope inference | K24: Not required for current backend scope. | L24: VendNet is a Spring REST API/backend in this repository; no browser frontend or DOM-rendering surface is present. | M24: Revisit if the application scope changes.
A25: V3.5 | B25: Browser Origin Separation | C25: V3.5.2 | D25: Verify that, if the application relies on the CORS preflight mechanism to prevent disallowed cross-origin use of sensitive functionality, it is not possible to call the functionality with a request which does not trigger a CORS-preflight request. This may require checking the values of the 'Origin' and 'Content-Type' request header fields or using an extra header field that is not a CORS-safelisted header-field. | E25: 1 | F25: N/A | G25: Automatically marked out of scope: VendNet is a Spring REST API/backend in this repository; no browser frontend or DOM-rendering surface is present. | H25: Automated scope inference | I25: Out of scope for VendNet as currently implemented, or the requirement does not apply to this REST API/backend. | J25: Scope inference | K25: Not required for current backend scope. | L25: VendNet is a Spring REST API/backend in this repository; no browser frontend or DOM-rendering surface is present. | M25: Revisit if the application scope changes.
A26: V3.5 | B26: Browser Origin Separation | C26: V3.5.3 | D26: Verify that HTTP requests to sensitive functionality use appropriate HTTP methods such as POST, PUT, PATCH, or DELETE, and not methods defined by the HTTP specification as "safe" such as HEAD, OPTIONS, or GET. Alternatively, strict validation of the Sec-Fetch-* request header fields can be used to ensure that the request did not originate from an inappropriate cross-origin call, a navigation request, or a resource load (such as an image source) where this is not expected. | E26: 1 | F26: N/A | G26: Automatically marked out of scope: VendNet is a Spring REST API/backend in this repository; no browser frontend or DOM-rendering surface is present. | H26: Automated scope inference | I26: Out of scope for VendNet as currently implemented, or the requirement does not apply to this REST API/backend. | J26: Scope inference | K26: Not required for current backend scope. | L26: VendNet is a Spring REST API/backend in this repository; no browser frontend or DOM-rendering surface is present. | M26: Revisit if the application scope changes.
A27: V3.5 | B27: Browser Origin Separation | C27: V3.5.4 | D27: Verify that separate applications are hosted on different hostnames to leverage the restrictions provided by same-origin policy, including how documents or scripts loaded by one origin can interact with resources from another origin and hostname-based restrictions on cookies. | E27: 2 | F27: N/A | G27: Automatically marked out of scope: VendNet is a Spring REST API/backend in this repository; no browser frontend or DOM-rendering surface is present. | H27: Automated scope inference | I27: Out of scope for VendNet as currently implemented, or the requirement does not apply to this REST API/backend. | J27: Scope inference | K27: Not required for current backend scope. | L27: VendNet is a Spring REST API/backend in this repository; no browser frontend or DOM-rendering surface is present. | M27: Revisit if the application scope changes.
A28: V3.5 | B28: Browser Origin Separation | C28: V3.5.5 | D28: Verify that messages received by the postMessage interface are discarded if the origin of the message is not trusted, or if the syntax of the message is invalid. | E28: 2 | F28: N/A | G28: Automatically marked out of scope: VendNet is a Spring REST API/backend in this repository; no browser frontend or DOM-rendering surface is present. | H28: Automated scope inference | I28: Out of scope for VendNet as currently implemented, or the requirement does not apply to this REST API/backend. | J28: Scope inference | K28: Not required for current backend scope. | L28: VendNet is a Spring REST API/backend in this repository; no browser frontend or DOM-rendering surface is present. | M28: Revisit if the application scope changes.
A29: V3.5 | B29: Browser Origin Separation | C29: V3.5.6 | D29: Verify that JSONP functionality is not enabled anywhere across the application to avoid Cross-Site Script Inclusion (XSSI) attacks. | E29: 3 | F29: N/A | G29: Automatically marked out of scope: VendNet is a Spring REST API/backend in this repository; no browser frontend or DOM-rendering surface is present. | H29: Automated scope inference | I29: Out of scope for VendNet as currently implemented, or the requirement does not apply to this REST API/backend. | J29: Scope inference | K29: Not required for current backend scope. | L29: VendNet is a Spring REST API/backend in this repository; no browser frontend or DOM-rendering surface is present. | M29: Revisit if the application scope changes.
A30: V3.5 | B30: Browser Origin Separation | C30: V3.5.7 | D30: Verify that data requiring authorization is not included in script resource responses, like JavaScript files, to prevent Cross-Site Script Inclusion (XSSI) attacks. | E30: 3 | F30: N/A | G30: Automatically marked out of scope: VendNet is a Spring REST API/backend in this repository; no browser frontend or DOM-rendering surface is present. | H30: Automated scope inference | I30: Out of scope for VendNet as currently implemented, or the requirement does not apply to this REST API/backend. | J30: Scope inference | K30: Not required for current backend scope. | L30: VendNet is a Spring REST API/backend in this repository; no browser frontend or DOM-rendering surface is present. | M30: Revisit if the application scope changes.
A31: V3.5 | B31: Browser Origin Separation | C31: V3.5.8 | D31: Verify that authenticated resources (such as images, videos, scripts, and other documents) can be loaded or embedded on behalf of the user only when intended. This can be accomplished by strict validation of the Sec-Fetch-* HTTP request header fields to ensure that the request did not originate from an inappropriate cross-origin call, or by setting a restrictive Cross-Origin-Resource-Policy HTTP response header field to instruct the browser to block returned content. | E31: 3 | F31: N/A | G31: Automatically marked out of scope: VendNet is a Spring REST API/backend in this repository; no browser frontend or DOM-rendering surface is present. | H31: Automated scope inference | I31: Out of scope for VendNet as currently implemented, or the requirement does not apply to this REST API/backend. | J31: Scope inference | K31: Not required for current backend scope. | L31: VendNet is a Spring REST API/backend in this repository; no browser frontend or DOM-rendering surface is present. | M31: Revisit if the application scope changes.
A32: V3.6 | B32: External Resource Integrity
A33: V3.6 | B33: External Resource Integrity | C33: V3.6.1 | D33: Verify that client-side assets, such as JavaScript libraries, CSS, or web fonts, are only hosted externally (e.g., on a Content Delivery Network) if the resource is static and versioned and Subresource Integrity (SRI) is used to validate the integrity of the asset. If this is not possible, there should be a documented security decision to justify this for each resource. | E33: 3 | F33: N/A | G33: Automatically marked out of scope: VendNet is a Spring REST API/backend in this repository; no browser frontend or DOM-rendering surface is present. | H33: Automated scope inference | I33: Out of scope for VendNet as currently implemented, or the requirement does not apply to this REST API/backend. | J33: Scope inference | K33: Not required for current backend scope. | L33: VendNet is a Spring REST API/backend in this repository; no browser frontend or DOM-rendering surface is present. | M33: Revisit if the application scope changes.
A34: V3.7 | B34: Other Browser Security Considerations
A35: V3.7 | B35: Other Browser Security Considerations | C35: V3.7.1 | D35: Verify that the application only uses client-side technologies which are still supported and considered secure. Examples of technologies which do not meet this requirement include NSAPI plugins, Flash, Shockwave, ActiveX, Silverlight, NACL, or client-side Java applets. | E35: 2 | F35: N/A | G35: Automatically marked out of scope: VendNet is a Spring REST API/backend in this repository; no browser frontend or DOM-rendering surface is present. | H35: Automated scope inference | I35: Out of scope for VendNet as currently implemented, or the requirement does not apply to this REST API/backend. | J35: Scope inference | K35: Not required for current backend scope. | L35: VendNet is a Spring REST API/backend in this repository; no browser frontend or DOM-rendering surface is present. | M35: Revisit if the application scope changes.
A36: V3.7 | B36: Other Browser Security Considerations | C36: V3.7.2 | D36: Verify that the application will only automatically redirect the user to a different hostname or domain (which is not controlled by the application) where the destination appears on an allowlist. | E36: 2 | F36: N/A | G36: Automatically marked out of scope: VendNet is a Spring REST API/backend in this repository; no browser frontend or DOM-rendering surface is present. | H36: Automated scope inference | I36: Out of scope for VendNet as currently implemented, or the requirement does not apply to this REST API/backend. | J36: Scope inference | K36: Not required for current backend scope. | L36: VendNet is a Spring REST API/backend in this repository; no browser frontend or DOM-rendering surface is present. | M36: Revisit if the application scope changes.
A37: V3.7 | B37: Other Browser Security Considerations | C37: V3.7.3 | D37: Verify that the application shows a notification when the user is being redirected to a URL outside of the application's control, with an option to cancel the navigation. | E37: 3 | F37: N/A | G37: Automatically marked out of scope: VendNet is a Spring REST API/backend in this repository; no browser frontend or DOM-rendering surface is present. | H37: Automated scope inference | I37: Out of scope for VendNet as currently implemented, or the requirement does not apply to this REST API/backend. | J37: Scope inference | K37: Not required for current backend scope. | L37: VendNet is a Spring REST API/backend in this repository; no browser frontend or DOM-rendering surface is present. | M37: Revisit if the application scope changes.
A38: V3.7 | B38: Other Browser Security Considerations | C38: V3.7.4 | D38: Verify that the application's top-level domain (e.g., site.tld) is added to the public preload list for HTTP Strict Transport Security (HSTS). This ensures that the use of TLS for the application is built directly into the main browsers, rather than relying only on the Strict-Transport-Security response header field. | E38: 3 | F38: N/A | G38: Automatically marked out of scope: VendNet is a Spring REST API/backend in this repository; no browser frontend or DOM-rendering surface is present. | H38: Automated scope inference | I38: Out of scope for VendNet as currently implemented, or the requirement does not apply to this REST API/backend. | J38: Scope inference | K38: Not required for current backend scope. | L38: VendNet is a Spring REST API/backend in this repository; no browser frontend or DOM-rendering surface is present. | M38: Revisit if the application scope changes.
A39: V3.7 | B39: Other Browser Security Considerations | C39: V3.7.5 | D39: Verify that the application behaves as documented (such as warning the user or blocking access) if the browser used to access the application does not support the expected security features. | E39: 3 | F39: N/A | G39: Automatically marked out of scope: VendNet is a Spring REST API/backend in this repository; no browser frontend or DOM-rendering surface is present. | H39: Automated scope inference | I39: Out of scope for VendNet as currently implemented, or the requirement does not apply to this REST API/backend. | J39: Scope inference | K39: Not required for current backend scope. | L39: VendNet is a Spring REST API/backend in this repository; no browser frontend or DOM-rendering surface is present. | M39: Revisit if the application scope changes.

Sheet V4 - API and Web Service
A1: Section ID | B1: Section Name | C1: Req ID | D1: Description | E1: Level | F1: Status | G1: Observations | H1: Reference / Link | I1: DX Status Meaning | J1: Evidence Type | K1: Automated Evidence | L1: Evidence Source | M1: Next Action
A2: V4.1 | B2: Generic Web Service Security
A3: V4.1 | B3: Generic Web Service Security | C3: V4.1.1 | D3: Verify that every HTTP response with a message body contains a Content-Type header field that matches the actual content of the response, including the charset parameter to specify safe character encoding (e.g., UTF-8, ISO-8859-1) according to IANA Media Types, such as "text/", "/+xml" and "/xml". | E3: 1 | F3: N/A | G3: Automatically marked out of scope: No XML/SOAP API surface is present; controllers return JSON REST responses. | H3: Automated scope inference | I3: Out of scope for VendNet as currently implemented, or the requirement does not apply to this REST API/backend. | J3: Scope inference | K3: Not required for current backend scope. | L3: No XML/SOAP API surface is present; controllers return JSON REST responses. | M3: Revisit if the application scope changes.
A4: V4.1 | B4: Generic Web Service Security | C4: V4.1.2 | D4: Verify that only user-facing endpoints (intended for manual web-browser access) automatically redirect from HTTP to HTTPS, while other services or endpoints do not implement transparent redirects. This is to avoid a situation where a client is erroneously sending unencrypted HTTP requests, but since the requests are being automatically redirected to HTTPS, the leakage of sensitive data goes undiscovered. | E4: 2 | F4: N/A | G4: Automatically marked out of scope: No browser-rendered frontend surface is present in this repository. | H4: Automated scope inference | I4: Out of scope for VendNet as currently implemented, or the requirement does not apply to this REST API/backend. | J4: Scope inference | K4: Not required for current backend scope. | L4: No browser-rendered frontend surface is present in this repository. | M4: Revisit if the application scope changes.
A5: V4.1 | B5: Generic Web Service Security | C5: V4.1.3 | D5: Verify that any HTTP header field used by the application and set by an intermediary layer, such as a load balancer, a web proxy, or a backend-for-frontend service, cannot be overridden by the end-user. Example headers might include X-Real-IP, X-Forwarded-*, or X-User-ID. | E5: 2 | F5: Compliant | G5: Automatically marked compliant from passing evidence: safe JSON response/error surface. | H5: SR-14; GlobalExceptionHandlerTest; ControllerIntegrationTests; centralized safe error handling detected | I5: Automatically inferred as implemented or justified from passing tests, source code, configuration, or build artifacts. | J5: Automated repository evidence | K5: GlobalExceptionHandlerTest; ControllerIntegrationTests; centralized safe error handling detected | L5: safe JSON response/error surface | M5: Keep make asvs-tracker passing; reassess if code, tests, or scope changes.
A6: V4.1 | B6: Generic Web Service Security | C6: V4.1.4 | D6: Verify that only HTTP methods that are explicitly supported by the application or its API (including OPTIONS during preflight requests) can be used and that unused methods are blocked. | E6: 3 | F6: Compliant | G6: Automatically marked compliant from passing evidence: safe JSON response/error surface. | H6: SR-14; GlobalExceptionHandlerTest; ControllerIntegrationTests; centralized safe error handling detected | I6: Automatically inferred as implemented or justified from passing tests, source code, configuration, or build artifacts. | J6: Automated repository evidence | K6: GlobalExceptionHandlerTest; ControllerIntegrationTests; centralized safe error handling detected | L6: safe JSON response/error surface | M6: Keep make asvs-tracker passing; reassess if code, tests, or scope changes.
A7: V4.1 | B7: Generic Web Service Security | C7: V4.1.5 | D7: Verify that per-message digital signatures are used to provide additional assurance on top of transport protections for requests or transactions which are highly sensitive or which traverse a number of systems. | E7: 3 | F7: Compliant | G7: Automatically marked compliant from passing evidence: transaction and stock consistency; server-side price enforcement; stock limit validation; client-supplied price abuse-case regression; TOCTOU/stock race abuse-case regression. | H7: SR-15; SR-24; SR-25; AC-03; AC-07; SaleServiceTest; SlotServiceTest; AbuseCaseRegressionTest | I7: Automatically inferred as implemented or justified from passing tests, source code, configuration, or build artifacts. | J7: Automated repository evidence | K7: SaleServiceTest; SlotServiceTest; AbuseCaseRegressionTest | L7: transaction and stock consistency; server-side price enforcement; stock limit validation; client-supplied price abuse-case regression; TOCTOU/stock race abuse-case regression | M7: Keep make asvs-tracker passing; reassess if code, tests, or scope changes.
A8: V4.2 | B8: HTTP Message Structure Validation
A9: V4.2 | B9: HTTP Message Structure Validation | C9: V4.2.1 | D9: Verify that all application components (including load balancers, firewalls, and application servers) determine boundaries of incoming HTTP messages using the appropriate mechanism for the HTTP version to prevent HTTP request smuggling. In HTTP/1.x, if a Transfer-Encoding header field is present, the Content-Length header must be ignored per RFC 2616. When using HTTP/2 or HTTP/3, if a Content-Length header field is present, the receiver must ensure that it is consistent with the length of the DATA frames. | E9: 2 | F9: Compliant | G9: Automatically marked compliant from passing evidence: safe JSON response/error surface; dependency governance and SBOM; dependency update monitoring; pinned dependency rules. | H9: SR-14; SR-32; SR-33; SR-34; GlobalExceptionHandlerTest; ControllerIntegrationTests; Maven Enforcer; CycloneDX SBOM; Dependabot; pom.xml; SCA/SBOM/enforcer configuration detected; centralized safe error handling detected | I9: Automatically inferred as implemented or justified from passing tests, source code, configuration, or build artifacts. | J9: Automated repository evidence | K9: GlobalExceptionHandlerTest; ControllerIntegrationTests; Maven Enforcer; CycloneDX SBOM; Dependabot; pom.xml; SCA/SBOM/enforcer configuration detected; centralized safe error handling detected | L9: safe JSON response/error surface; dependency governance and SBOM; dependency update monitoring; pinned dependency rules | M9: Keep make asvs-tracker passing; reassess if code, tests, or scope changes.
A10: V4.2 | B10: HTTP Message Structure Validation | C10: V4.2.2 | D10: Verify that when generating HTTP messages, the Content-Length header field does not conflict with the length of the content as determined by the framing of the HTTP protocol, in order to prevent request smuggling attacks. | E10: 3 | F10: Compliant | G10: Automatically marked compliant from passing evidence: safe JSON response/error surface. | H10: SR-14; GlobalExceptionHandlerTest; ControllerIntegrationTests; centralized safe error handling detected | I10: Automatically inferred as implemented or justified from passing tests, source code, configuration, or build artifacts. | J10: Automated repository evidence | K10: GlobalExceptionHandlerTest; ControllerIntegrationTests; centralized safe error handling detected | L10: safe JSON response/error surface | M10: Keep make asvs-tracker passing; reassess if code, tests, or scope changes.
A11: V4.2 | B11: HTTP Message Structure Validation | C11: V4.2.3 | D11: Verify that the application does not send nor accept HTTP/2 or HTTP/3 messages with connection-specific header fields such as Transfer-Encoding to prevent response splitting and header injection attacks. | E11: 3 | F11: Compliant | G11: Automatically marked compliant from passing evidence: SQL injection regression and taint checks; SQL injection abuse-case regression. | H11: SR-09; AC-05; AbuseCaseRegressionTest; IastIntegrationTest | I11: Automatically inferred as implemented or justified from passing tests, source code, configuration, or build artifacts. | J11: Automated repository evidence | K11: AbuseCaseRegressionTest; IastIntegrationTest | L11: SQL injection regression and taint checks; SQL injection abuse-case regression | M11: Keep make asvs-tracker passing; reassess if code, tests, or scope changes.
A12: V4.2 | B12: HTTP Message Structure Validation | C12: V4.2.4 | D12: Verify that the application only accepts HTTP/2 and HTTP/3 requests where the header fields and values do not contain any CR (\r), LF (\n), or CRLF (\r\n) sequences, to prevent header injection attacks. | E12: 3 | F12: Compliant | G12: Automatically marked compliant from passing evidence: dependency governance and SBOM; SQL injection regression and taint checks; SQL injection abuse-case regression. | H12: SR-32; SR-09; AC-05; Maven Enforcer; CycloneDX SBOM; AbuseCaseRegressionTest; IastIntegrationTest; SCA/SBOM/enforcer configuration detected | I12: Automatically inferred as implemented or justified from passing tests, source code, configuration, or build artifacts. | J12: Automated repository evidence | K12: Maven Enforcer; CycloneDX SBOM; AbuseCaseRegressionTest; IastIntegrationTest; SCA/SBOM/enforcer configuration detected | L12: dependency governance and SBOM; SQL injection regression and taint checks; SQL injection abuse-case regression | M12: Keep make asvs-tracker passing; reassess if code, tests, or scope changes.
A13: V4.2 | B13: HTTP Message Structure Validation | C13: V4.2.5 | D13: Verify that, if the application (backend or frontend) builds and sends requests, it uses validation, sanitization, or other mechanisms to avoid creating URIs (such as for API calls) or HTTP request header fields (such as Authorization or Cookie), which are too long to be accepted by the receiving component. This could cause a denial of service, such as when sending an overly long request (e.g., a long cookie header field), which results in the server always responding with an error status. | E13: 3 | F13: Compliant | G13: Automatically marked compliant from passing evidence: stock limit validation; RBAC roles and endpoint isolation; controller/service authorization guardrails; user data access isolation; input shape/range validation; unknown-field rejection; payload/request limit coverage; dependency governance and SBOM; dependency update monitoring; pinned dependency rules; authentication audit logging; sensitive log data checks; safe error response checks. | H13: SR-25; SR-02; SR-06; SR-08; SR-28; SR-29; SR-30; SR-32; SR-33; SR-34; SR-37; SR-45; SR-46; SlotServiceTest; SaleServiceTest; RbacIntegrationTest; SecurityAnnotationArchTest; SystemFunctionalTests; ControllerIntegrationTests; ControllerUnitTests; GlobalExceptionHandlerTest; application.properties; Maven Enforcer; CycloneDX SBOM; Dependabot; pom.xml; AuthServiceTest; AuditLoggerTest; Spring method security and RBAC annotations detected; Bean Validation and request-shape controls detected; audit logging implementation detected; SCA/SBOM/enforcer configuration detected; centralized safe error handling detected | I13: Automatically inferred as implemented or justified from passing tests, source code, configuration, or build artifacts. | J13: Automated repository evidence | K13: SlotServiceTest; SaleServiceTest; RbacIntegrationTest; SecurityAnnotationArchTest; SystemFunctionalTests; ControllerIntegrationTests; ControllerUnitTests; GlobalExceptionHandlerTest; application.properties; Maven Enforcer; CycloneDX SBOM; Dependabot; pom.xml; AuthServiceTest; AuditLoggerTest; Spring method security and RBAC annotations detected; Bean Validation and request-shape controls detected; audit logging implementation detected; SCA/SBOM/enforcer configuration detected; centralized safe error handling detected | L13: stock limit validation; RBAC roles and endpoint isolation; controller/service authorization guardrails; user data access isolation; input shape/range validation; unknown-field rejection; payload/request limit coverage; dependency governance and SBOM; dependency update monitoring; pinned dependency rules; authentication audit logging; sensitive log data checks; safe error response checks | M13: Keep make asvs-tracker passing; reassess if code, tests, or scope changes.
A14: V4.3 | B14: GraphQL
A15: V4.3 | B15: GraphQL | C15: V4.3.1 | D15: Verify that a query allowlist, depth limiting, amount limiting, or query cost analysis is used to prevent GraphQL or data layer expression Denial of Service (DoS) as a result of expensive, nested queries. | E15: 2 | F15: N/A | G15: Automatically marked out of scope: No GraphQL endpoint or GraphQL dependency is present. | H15: Automated scope inference | I15: Out of scope for VendNet as currently implemented, or the requirement does not apply to this REST API/backend. | J15: Scope inference | K15: Not required for current backend scope. | L15: No GraphQL endpoint or GraphQL dependency is present. | M15: Revisit if the application scope changes.
A16: V4.3 | B16: GraphQL | C16: V4.3.2 | D16: Verify that GraphQL introspection queries are disabled in the production environment unless the GraphQL API is meant to be used by other parties. | E16: 2 | F16: N/A | G16: Automatically marked out of scope: No GraphQL endpoint or GraphQL dependency is present. | H16: Automated scope inference | I16: Out of scope for VendNet as currently implemented, or the requirement does not apply to this REST API/backend. | J16: Scope inference | K16: Not required for current backend scope. | L16: No GraphQL endpoint or GraphQL dependency is present. | M16: Revisit if the application scope changes.
A17: V4.4 | B17: WebSocket
A18: V4.4 | B18: WebSocket | C18: V4.4.1 | D18: Verify that WebSocket over TLS (WSS) is used for all WebSocket connections. | E18: 1 | F18: N/A | G18: Automatically marked out of scope: No WebSocket endpoint or WebSocket dependency is present. | H18: Automated scope inference | I18: Out of scope for VendNet as currently implemented, or the requirement does not apply to this REST API/backend. | J18: Scope inference | K18: Not required for current backend scope. | L18: No WebSocket endpoint or WebSocket dependency is present. | M18: Revisit if the application scope changes.
A19: V4.4 | B19: WebSocket | C19: V4.4.2 | D19: Verify that, during the initial HTTP WebSocket handshake, the Origin header field is checked against a list of origins allowed for the application. | E19: 2 | F19: N/A | G19: Automatically marked out of scope: No WebSocket endpoint or WebSocket dependency is present. | H19: Automated scope inference | I19: Out of scope for VendNet as currently implemented, or the requirement does not apply to this REST API/backend. | J19: Scope inference | K19: Not required for current backend scope. | L19: No WebSocket endpoint or WebSocket dependency is present. | M19: Revisit if the application scope changes.
A20: V4.4 | B20: WebSocket | C20: V4.4.3 | D20: Verify that, if the application's standard session management cannot be used, dedicated tokens are being used for this, which comply with the relevant Session Management security requirements. | E20: 2 | F20: Compliant | G20: Automatically marked compliant from passing evidence: JWT signature and algorithm validation; JWT key strength and server-side signing. | H20: SR-03; SR-04; AbuseCaseRegressionTest; JwtServiceTest; JwtAuthenticationFilterTest; JWT service and signing/filter code detected | I20: Automatically inferred as implemented or justified from passing tests, source code, configuration, or build artifacts. | J20: Automated repository evidence | K20: AbuseCaseRegressionTest; JwtServiceTest; JwtAuthenticationFilterTest; JWT service and signing/filter code detected | L20: JWT signature and algorithm validation; JWT key strength and server-side signing | M20: Keep make asvs-tracker passing; reassess if code, tests, or scope changes.
A21: V4.4 | B21: WebSocket | C21: V4.4.4 | D21: Verify that dedicated WebSocket session management tokens are initially obtained or validated through the previously authenticated HTTPS session when transitioning an existing HTTPS session to a WebSocket channel. | E21: 2 | F21: N/A | G21: Automatically marked out of scope: No WebSocket endpoint or WebSocket dependency is present. | H21: Automated scope inference | I21: Out of scope for VendNet as currently implemented, or the requirement does not apply to this REST API/backend. | J21: Scope inference | K21: Not required for current backend scope. | L21: No WebSocket endpoint or WebSocket dependency is present. | M21: Revisit if the application scope changes.

Sheet V5 - File Handling
A1: Section ID | B1: Section Name | C1: Req ID | D1: Description | E1: Level | F1: Status | G1: Observations | H1: Reference / Link | I1: DX Status Meaning | J1: Evidence Type | K1: Automated Evidence | L1: Evidence Source | M1: Next Action
A2: V5.1 | B2: File Handling Documentation
A3: V5.1 | B3: File Handling Documentation | C3: V5.1.1 | D3: Verify that the documentation defines the permitted file types, expected file extensions, and maximum size (including unpacked size) for each upload feature. Additionally, ensure that the documentation specifies how files are made safe for end-users to download and process, such as how the application behaves when a malicious file is detected. | E3: 2 | F3: Compliant | G3: Automatically marked compliant from passing evidence: path traversal and report sandboxing; unsafe path/link handling; path traversal abuse-case regression. | H3: SR-26; SR-27; AC-06; PathValidatorImplTest; ReportDirectoryServiceImplTest; AbuseCaseRegressionTest; path validation and report sandbox code detected | I3: Automatically inferred as implemented or justified from passing tests, source code, configuration, or build artifacts. | J3: Automated repository evidence | K3: PathValidatorImplTest; ReportDirectoryServiceImplTest; AbuseCaseRegressionTest; path validation and report sandbox code detected | L3: path traversal and report sandboxing; unsafe path/link handling; path traversal abuse-case regression | M3: Keep make asvs-tracker passing; reassess if code, tests, or scope changes.
A4: V5.2 | B4: File Upload and Content
A5: V5.2 | B5: File Upload and Content | C5: V5.2.1 | D5: Verify that the application will only accept files of a size which it can process without causing a loss of performance or a denial of service attack. | E5: 1 | F5: Compliant | G5: Automatically marked compliant from passing evidence: payload/request limit coverage; path traversal and report sandboxing; unsafe path/link handling; path traversal abuse-case regression. | H5: SR-30; SR-26; SR-27; AC-06; SystemFunctionalTests; application.properties; PathValidatorImplTest; ReportDirectoryServiceImplTest; AbuseCaseRegressionTest; Bean Validation and request-shape controls detected; path validation and report sandbox code detected | I5: Automatically inferred as implemented or justified from passing tests, source code, configuration, or build artifacts. | J5: Automated repository evidence | K5: SystemFunctionalTests; application.properties; PathValidatorImplTest; ReportDirectoryServiceImplTest; AbuseCaseRegressionTest; Bean Validation and request-shape controls detected; path validation and report sandbox code detected | L5: payload/request limit coverage; path traversal and report sandboxing; unsafe path/link handling; path traversal abuse-case regression | M5: Keep make asvs-tracker passing; reassess if code, tests, or scope changes.
A6: V5.2 | B6: File Upload and Content | C6: V5.2.2 | D6: Verify that when the application accepts a file, either on its own or within an archive such as a zip file, it checks if the file extension matches an expected file extension and validates that the contents correspond to the type represented by the extension. This includes, but is not limited to, checking the initial 'magic bytes', performing image re-writing, and using specialized libraries for file content validation. For L1, this can focus just on files which are used to make specific business or security decisions. For L2 and up, this must apply to all files being accepted. | E6: 1 | F6: Compliant | G6: Automatically marked compliant from passing evidence: input shape/range validation; unknown-field rejection; payload/request limit coverage; path traversal and report sandboxing; unsafe path/link handling; path traversal abuse-case regression. | H6: SR-28; SR-29; SR-30; SR-26; SR-27; AC-06; ControllerIntegrationTests; SystemFunctionalTests; ControllerUnitTests; GlobalExceptionHandlerTest; application.properties; PathValidatorImplTest; ReportDirectoryServiceImplTest; AbuseCaseRegressionTest; Bean Validation and request-shape controls detected; path validation and report sandbox code detected | I6: Automatically inferred as implemented or justified from passing tests, source code, configuration, or build artifacts. | J6: Automated repository evidence | K6: ControllerIntegrationTests; SystemFunctionalTests; ControllerUnitTests; GlobalExceptionHandlerTest; application.properties; PathValidatorImplTest; ReportDirectoryServiceImplTest; AbuseCaseRegressionTest; Bean Validation and request-shape controls detected; path validation and report sandbox code detected | L6: input shape/range validation; unknown-field rejection; payload/request limit coverage; path traversal and report sandboxing; unsafe path/link handling; path traversal abuse-case regression | M6: Keep make asvs-tracker passing; reassess if code, tests, or scope changes.
A7: V5.2 | B7: File Upload and Content | C7: V5.2.3 | D7: Verify that the application checks compressed files (e.g., zip, gz, docx, odt) against maximum allowed uncompressed size and against maximum number of files before uncompressing the file. | E7: 2 | F7: Compliant | G7: Automatically marked compliant from passing evidence: path traversal and report sandboxing; unsafe path/link handling; path traversal abuse-case regression. | H7: SR-26; SR-27; AC-06; PathValidatorImplTest; ReportDirectoryServiceImplTest; AbuseCaseRegressionTest; path validation and report sandbox code detected | I7: Automatically inferred as implemented or justified from passing tests, source code, configuration, or build artifacts. | J7: Automated repository evidence | K7: PathValidatorImplTest; ReportDirectoryServiceImplTest; AbuseCaseRegressionTest; path validation and report sandbox code detected | L7: path traversal and report sandboxing; unsafe path/link handling; path traversal abuse-case regression | M7: Keep make asvs-tracker passing; reassess if code, tests, or scope changes.
A8: V5.2 | B8: File Upload and Content | C8: V5.2.4 | D8: Verify that a file size quota and maximum number of files per user are enforced to ensure that a single user cannot fill up the storage with too many files, or excessively large files. | E8: 3 | F8: Compliant | G8: Automatically marked compliant from passing evidence: path traversal and report sandboxing; unsafe path/link handling; path traversal abuse-case regression. | H8: SR-26; SR-27; AC-06; PathValidatorImplTest; ReportDirectoryServiceImplTest; AbuseCaseRegressionTest; path validation and report sandbox code detected | I8: Automatically inferred as implemented or justified from passing tests, source code, configuration, or build artifacts. | J8: Automated repository evidence | K8: PathValidatorImplTest; ReportDirectoryServiceImplTest; AbuseCaseRegressionTest; path validation and report sandbox code detected | L8: path traversal and report sandboxing; unsafe path/link handling; path traversal abuse-case regression | M8: Keep make asvs-tracker passing; reassess if code, tests, or scope changes.
A9: V5.2 | B9: File Upload and Content | C9: V5.2.5 | D9: Verify that the application does not allow uploading compressed files containing symlinks unless this is specifically required (in which case it will be necessary to enforce an allowlist of the files that can be symlinked to). | E9: 3 | F9: Compliant | G9: Automatically marked compliant from passing evidence: unsafe path/link handling; path traversal and report sandboxing; path traversal abuse-case regression. | H9: SR-27; SR-26; AC-06; PathValidatorImplTest; ReportDirectoryServiceImplTest; AbuseCaseRegressionTest; path validation and report sandbox code detected | I9: Automatically inferred as implemented or justified from passing tests, source code, configuration, or build artifacts. | J9: Automated repository evidence | K9: PathValidatorImplTest; ReportDirectoryServiceImplTest; AbuseCaseRegressionTest; path validation and report sandbox code detected | L9: unsafe path/link handling; path traversal and report sandboxing; path traversal abuse-case regression | M9: Keep make asvs-tracker passing; reassess if code, tests, or scope changes.
A10: V5.2 | B10: File Upload and Content | C10: V5.2.6 | D10: Verify that the application rejects uploaded images with a pixel size larger than the maximum allowed, to prevent pixel flood attacks. | E10: 3 | F10: Compliant | G10: Automatically marked compliant from passing evidence: path traversal and report sandboxing; unsafe path/link handling; path traversal abuse-case regression. | H10: SR-26; SR-27; AC-06; PathValidatorImplTest; ReportDirectoryServiceImplTest; AbuseCaseRegressionTest; path validation and report sandbox code detected | I10: Automatically inferred as implemented or justified from passing tests, source code, configuration, or build artifacts. | J10: Automated repository evidence | K10: PathValidatorImplTest; ReportDirectoryServiceImplTest; AbuseCaseRegressionTest; path validation and report sandbox code detected | L10: path traversal and report sandboxing; unsafe path/link handling; path traversal abuse-case regression | M10: Keep make asvs-tracker passing; reassess if code, tests, or scope changes.
A11: V5.3 | B11: File Storage
A12: V5.3 | B12: File Storage | C12: V5.3.1 | D12: Verify that files uploaded or generated by untrusted input and stored in a public folder, are not executed as server-side program code when accessed directly with an HTTP request. | E12: 1 | F12: Compliant | G12: Automatically marked compliant from passing evidence: input shape/range validation; unknown-field rejection; payload/request limit coverage; path traversal and report sandboxing; unsafe path/link handling; path traversal abuse-case regression. | H12: NFR-11; SR-28; SR-29; SR-30; SR-26; SR-27; AC-06; ControllerIntegrationTests; SystemFunctionalTests; ControllerUnitTests; GlobalExceptionHandlerTest; application.properties; PathValidatorImplTest; ReportDirectoryServiceImplTest; AbuseCaseRegressionTest; Bean Validation and request-shape controls detected; path validation and report sandbox code detected | I12: Automatically inferred as implemented or justified from passing tests, source code, configuration, or build artifacts. | J12: Automated repository evidence | K12: ControllerIntegrationTests; SystemFunctionalTests; ControllerUnitTests; GlobalExceptionHandlerTest; application.properties; PathValidatorImplTest; ReportDirectoryServiceImplTest; AbuseCaseRegressionTest; Bean Validation and request-shape controls detected; path validation and report sandbox code detected | L12: input shape/range validation; unknown-field rejection; payload/request limit coverage; path traversal and report sandboxing; unsafe path/link handling; path traversal abuse-case regression | M12: Keep make asvs-tracker passing; reassess if code, tests, or scope changes.
A13: V5.3 | B13: File Storage | C13: V5.3.2 | D13: Verify that when the application creates file paths for file operations, instead of user-submitted filenames, it uses internally generated or trusted data, or if user-submitted filenames or file metadata must be used, strict validation and sanitization must be applied. This is to protect against path traversal, local or remote file inclusion (LFI, RFI), and server-side request forgery (SSRF) attacks. | E13: 1 | F13: Compliant | G13: Automatically marked compliant from passing evidence: path traversal and report sandboxing; input shape/range validation; unknown-field rejection; payload/request limit coverage; unsafe path/link handling; path traversal abuse-case regression. | H13: SR-26; SR-28; SR-29; SR-30; SR-27; AC-06; PathValidatorImplTest; ReportDirectoryServiceImplTest; AbuseCaseRegressionTest; ControllerIntegrationTests; SystemFunctionalTests; ControllerUnitTests; GlobalExceptionHandlerTest; application.properties; Bean Validation and request-shape controls detected; path validation and report sandbox code detected | I13: Automatically inferred as implemented or justified from passing tests, source code, configuration, or build artifacts. | J13: Automated repository evidence | K13: PathValidatorImplTest; ReportDirectoryServiceImplTest; AbuseCaseRegressionTest; ControllerIntegrationTests; SystemFunctionalTests; ControllerUnitTests; GlobalExceptionHandlerTest; application.properties; Bean Validation and request-shape controls detected; path validation and report sandbox code detected | L13: path traversal and report sandboxing; input shape/range validation; unknown-field rejection; payload/request limit coverage; unsafe path/link handling; path traversal abuse-case regression | M13: Keep make asvs-tracker passing; reassess if code, tests, or scope changes.
A14: V5.3 | B14: File Storage | C14: V5.3.3 | D14: Verify that server-side file processing, such as file decompression, ignores user-provided path information to prevent vulnerabilities such as zip slip. | E14: 3 | F14: Compliant | G14: Automatically marked compliant from passing evidence: path traversal and report sandboxing; unsafe path/link handling; path traversal abuse-case regression. | H14: SR-26; SR-27; AC-06; PathValidatorImplTest; ReportDirectoryServiceImplTest; AbuseCaseRegressionTest; path validation and report sandbox code detected | I14: Automatically inferred as implemented or justified from passing tests, source code, configuration, or build artifacts. | J14: Automated repository evidence | K14: PathValidatorImplTest; ReportDirectoryServiceImplTest; AbuseCaseRegressionTest; path validation and report sandbox code detected | L14: path traversal and report sandboxing; unsafe path/link handling; path traversal abuse-case regression | M14: Keep make asvs-tracker passing; reassess if code, tests, or scope changes.
A15: V5.4 | B15: File Download
A16: V5.4 | B16: File Download | C16: V5.4.1 | D16: Verify that the application validates or ignores user-submitted filenames, including in a JSON, JSONP, or URL parameter and specifies a filename in the Content-Disposition header field in the response. | E16: 2 | F16: Compliant | G16: Automatically marked compliant from passing evidence: path traversal and report sandboxing; unsafe path/link handling; path traversal abuse-case regression. | H16: SR-26; SR-27; AC-06; PathValidatorImplTest; ReportDirectoryServiceImplTest; AbuseCaseRegressionTest; path validation and report sandbox code detected | I16: Automatically inferred as implemented or justified from passing tests, source code, configuration, or build artifacts. | J16: Automated repository evidence | K16: PathValidatorImplTest; ReportDirectoryServiceImplTest; AbuseCaseRegressionTest; path validation and report sandbox code detected | L16: path traversal and report sandboxing; unsafe path/link handling; path traversal abuse-case regression | M16: Keep make asvs-tracker passing; reassess if code, tests, or scope changes.
A17: V5.4 | B17: File Download | C17: V5.4.2 | D17: Verify that file names served (e.g., in HTTP response header fields or email attachments) are encoded or sanitized (e.g., following RFC 6266) to preserve document structure and prevent injection attacks. | E17: 2 | F17: Compliant | G17: Automatically marked compliant from passing evidence: path traversal and report sandboxing; SQL injection regression and taint checks; SQL injection abuse-case regression; unsafe path/link handling; path traversal abuse-case regression. | H17: SR-26; SR-09; AC-05; SR-27; AC-06; PathValidatorImplTest; ReportDirectoryServiceImplTest; AbuseCaseRegressionTest; IastIntegrationTest; path validation and report sandbox code detected | I17: Automatically inferred as implemented or justified from passing tests, source code, configuration, or build artifacts. | J17: Automated repository evidence | K17: PathValidatorImplTest; ReportDirectoryServiceImplTest; AbuseCaseRegressionTest; IastIntegrationTest; path validation and report sandbox code detected | L17: path traversal and report sandboxing; SQL injection regression and taint checks; SQL injection abuse-case regression; unsafe path/link handling; path traversal abuse-case regression | M17: Keep make asvs-tracker passing; reassess if code, tests, or scope changes.
A18: V5.4 | B18: File Download | C18: V5.4.3 | D18: Verify that files obtained from untrusted sources are scanned by antivirus scanners to prevent serving of known malicious content. | E18: 2 | F18: Compliant | G18: Automatically marked compliant from passing evidence: path traversal and report sandboxing; unsafe path/link handling; path traversal abuse-case regression. | H18: SR-26; SR-27; AC-06; PathValidatorImplTest; ReportDirectoryServiceImplTest; AbuseCaseRegressionTest; path validation and report sandbox code detected | I18: Automatically inferred as implemented or justified from passing tests, source code, configuration, or build artifacts. | J18: Automated repository evidence | K18: PathValidatorImplTest; ReportDirectoryServiceImplTest; AbuseCaseRegressionTest; path validation and report sandbox code detected | L18: path traversal and report sandboxing; unsafe path/link handling; path traversal abuse-case regression | M18: Keep make asvs-tracker passing; reassess if code, tests, or scope changes.

Sheet V6 - Authentication
A1: Section ID | B1: Section Name | C1: Req ID | D1: Description | E1: Level | F1: Status | G1: Observations | H1: Reference / Link | I1: DX Status Meaning | J1: Evidence Type | K1: Automated Evidence | L1: Evidence Source | M1: Next Action
A2: V6.1 | B2: Authentication Documentation
A3: V6.1 | B3: Authentication Documentation | C3: V6.1.1 | D3: Verify that application documentation defines how controls such as rate limiting, anti-automation, and adaptive response, are used to defend against attacks such as credential stuffing and password brute force. The documentation must make clear how these controls are configured and prevent malicious account lockout. | E3: 1 | F3: Compliant | G3: Automatically marked compliant from passing evidence: failed-login lockout behaviour; administrator MFA; account status validation. | H3: SR-07; NFR-07; SR-01; SR-05; AuthServiceTest; AuthControllerIntegrationTest; SystemFunctionalTests; MFA/TOTP code and tests detected | I3: Automatically inferred as implemented or justified from passing tests, source code, configuration, or build artifacts. | J3: Automated repository evidence | K3: AuthServiceTest; AuthControllerIntegrationTest; SystemFunctionalTests; MFA/TOTP code and tests detected | L3: failed-login lockout behaviour; administrator MFA; account status validation | M3: Keep make asvs-tracker passing; reassess if code, tests, or scope changes.
A4: V6.1 | B4: Authentication Documentation | C4: V6.1.2 | D4: Verify that a list of context-specific words is documented in order to prevent their use in passwords. The list could include permutations of organization names, product names, system identifiers, project codenames, department or role names, and similar. | E4: 2 | F4: Compliant | G4: Automatically marked compliant from passing evidence: administrator MFA; account status validation; failed-login lockout behaviour; RBAC roles and endpoint isolation; controller/service authorization guardrails; user data access isolation. | H4: SR-01; SR-05; SR-07; SR-02; SR-06; SR-08; AuthServiceTest; AuthControllerIntegrationTest; SystemFunctionalTests; RbacIntegrationTest; SecurityAnnotationArchTest; MFA/TOTP code and tests detected; Spring method security and RBAC annotations detected | I4: Automatically inferred as implemented or justified from passing tests, source code, configuration, or build artifacts. | J4: Automated repository evidence | K4: AuthServiceTest; AuthControllerIntegrationTest; SystemFunctionalTests; RbacIntegrationTest; SecurityAnnotationArchTest; MFA/TOTP code and tests detected; Spring method security and RBAC annotations detected | L4: administrator MFA; account status validation; failed-login lockout behaviour; RBAC roles and endpoint isolation; controller/service authorization guardrails; user data access isolation | M4: Keep make asvs-tracker passing; reassess if code, tests, or scope changes.
A5: V6.1 | B5: Authentication Documentation | C5: V6.1.3 | D5: Verify that, if the application includes multiple authentication pathways, these are all documented together with the security controls and authentication strength which must be consistently enforced across them. | E5: 2 | F5: Compliant | G5: Automatically marked compliant from passing evidence: administrator MFA; user data access isolation; account status validation; failed-login lockout behaviour; path traversal and report sandboxing; unsafe path/link handling; path traversal abuse-case regression. | H5: SR-01; SR-08; NFR-15; SR-05; SR-07; SR-26; SR-27; AC-06; AuthServiceTest; AuthControllerIntegrationTest; RbacIntegrationTest; SystemFunctionalTests; PathValidatorImplTest; ReportDirectoryServiceImplTest; AbuseCaseRegressionTest; MFA/TOTP code and tests detected; Spring method security and RBAC annotations detected; path validation and report sandbox code detected | I5: Automatically inferred as implemented or justified from passing tests, source code, configuration, or build artifacts. | J5: Automated repository evidence | K5: AuthServiceTest; AuthControllerIntegrationTest; RbacIntegrationTest; SystemFunctionalTests; PathValidatorImplTest; ReportDirectoryServiceImplTest; AbuseCaseRegressionTest; MFA/TOTP code and tests detected; Spring method security and RBAC annotations detected; path validation and report sandbox code detected | L5: administrator MFA; user data access isolation; account status validation; failed-login lockout behaviour; path traversal and report sandboxing; unsafe path/link handling; path traversal abuse-case regression | M5: Keep make asvs-tracker passing; reassess if code, tests, or scope changes.
A6: V6.2 | B6: Password Security
A7: V6.2 | B7: Password Security | C7: V6.2.1 | D7: Verify that user set passwords are at least 8 characters in length although a minimum of 15 characters is strongly recommended. | E7: 1 | F7: Compliant | G7: Automatically marked compliant from passing evidence: administrator MFA; account status validation; failed-login lockout behaviour. | H7: SR-01; SR-05; SR-07; AuthServiceTest; AuthControllerIntegrationTest; SystemFunctionalTests; MFA/TOTP code and tests detected | I7: Automatically inferred as implemented or justified from passing tests, source code, configuration, or build artifacts. | J7: Automated repository evidence | K7: AuthServiceTest; AuthControllerIntegrationTest; SystemFunctionalTests; MFA/TOTP code and tests detected | L7: administrator MFA; account status validation; failed-login lockout behaviour | M7: Keep make asvs-tracker passing; reassess if code, tests, or scope changes.
A8: V6.2 | B8: Password Security | C8: V6.2.2 | D8: Verify that users can change their password. | E8: 1 | F8: Compliant | G8: Automatically marked compliant from passing evidence: administrator MFA; account status validation; failed-login lockout behaviour. | H8: SR-01; SR-05; SR-07; AuthServiceTest; AuthControllerIntegrationTest; SystemFunctionalTests; MFA/TOTP code and tests detected | I8: Automatically inferred as implemented or justified from passing tests, source code, configuration, or build artifacts. | J8: Automated repository evidence | K8: AuthServiceTest; AuthControllerIntegrationTest; SystemFunctionalTests; MFA/TOTP code and tests detected | L8: administrator MFA; account status validation; failed-login lockout behaviour | M8: Keep make asvs-tracker passing; reassess if code, tests, or scope changes.
A9: V6.2 | B9: Password Security | C9: V6.2.3 | D9: Verify that password change functionality requires the user's current and new password. | E9: 1 | F9: Compliant | G9: Automatically marked compliant from passing evidence: administrator MFA; account status validation; failed-login lockout behaviour. | H9: SR-01; SR-05; SR-07; AuthServiceTest; AuthControllerIntegrationTest; SystemFunctionalTests; MFA/TOTP code and tests detected | I9: Automatically inferred as implemented or justified from passing tests, source code, configuration, or build artifacts. | J9: Automated repository evidence | K9: AuthServiceTest; AuthControllerIntegrationTest; SystemFunctionalTests; MFA/TOTP code and tests detected | L9: administrator MFA; account status validation; failed-login lockout behaviour | M9: Keep make asvs-tracker passing; reassess if code, tests, or scope changes.
A10: V6.2 | B10: Password Security | C10: V6.2.4 | D10: Verify that passwords submitted during account registration or password change are checked against an available set of, at least, the top 3000 passwords which match the application's password policy, e.g. minimum length. | E10: 1 | F10: Compliant | G10: Automatically marked compliant from passing evidence: administrator MFA; account status validation; failed-login lockout behaviour. | H10: SR-01; SR-05; SR-07; AuthServiceTest; AuthControllerIntegrationTest; SystemFunctionalTests; MFA/TOTP code and tests detected | I10: Automatically inferred as implemented or justified from passing tests, source code, configuration, or build artifacts. | J10: Automated repository evidence | K10: AuthServiceTest; AuthControllerIntegrationTest; SystemFunctionalTests; MFA/TOTP code and tests detected | L10: administrator MFA; account status validation; failed-login lockout behaviour | M10: Keep make asvs-tracker passing; reassess if code, tests, or scope changes.
A11: V6.2 | B11: Password Security | C11: V6.2.5 | D11: Verify that passwords of any composition can be used, without rules limiting the type of characters permitted. There must be no requirement for a minimum number of upper or lower case characters, numbers, or special characters. | E11: 1 | F11: Compliant | G11: Automatically marked compliant from passing evidence: administrator MFA; account status validation; failed-login lockout behaviour. | H11: SR-01; SR-05; SR-07; AuthServiceTest; AuthControllerIntegrationTest; SystemFunctionalTests; MFA/TOTP code and tests detected | I11: Automatically inferred as implemented or justified from passing tests, source code, configuration, or build artifacts. | J11: Automated repository evidence | K11: AuthServiceTest; AuthControllerIntegrationTest; SystemFunctionalTests; MFA/TOTP code and tests detected | L11: administrator MFA; account status validation; failed-login lockout behaviour | M11: Keep make asvs-tracker passing; reassess if code, tests, or scope changes.
A12: V6.2 | B12: Password Security | C12: V6.2.6 | D12: Verify that password input fields use type=password to mask the entry. Applications may allow the user to temporarily view the entire masked password, or the last typed character of the password. | E12: 1 | F12: Compliant | G12: Automatically marked compliant from passing evidence: administrator MFA; account status validation; failed-login lockout behaviour; input shape/range validation; unknown-field rejection; payload/request limit coverage. | H12: SR-01; SR-05; SR-07; SR-28; SR-29; SR-30; AuthServiceTest; AuthControllerIntegrationTest; SystemFunctionalTests; ControllerIntegrationTests; ControllerUnitTests; GlobalExceptionHandlerTest; application.properties; MFA/TOTP code and tests detected; Bean Validation and request-shape controls detected | I12: Automatically inferred as implemented or justified from passing tests, source code, configuration, or build artifacts. | J12: Automated repository evidence | K12: AuthServiceTest; AuthControllerIntegrationTest; SystemFunctionalTests; ControllerIntegrationTests; ControllerUnitTests; GlobalExceptionHandlerTest; application.properties; MFA/TOTP code and tests detected; Bean Validation and request-shape controls detected | L12: administrator MFA; account status validation; failed-login lockout behaviour; input shape/range validation; unknown-field rejection; payload/request limit coverage | M12: Keep make asvs-tracker passing; reassess if code, tests, or scope changes.
A13: V6.2 | B13: Password Security | C13: V6.2.7 | D13: Verify that "paste" functionality, browser password helpers, and external password managers are permitted. | E13: 1 | F13: N/A | G13: Automatically marked out of scope: No browser-rendered frontend surface is present in this repository. | H13: Automated scope inference | I13: Out of scope for VendNet as currently implemented, or the requirement does not apply to this REST API/backend. | J13: Scope inference | K13: Not required for current backend scope. | L13: No browser-rendered frontend surface is present in this repository. | M13: Revisit if the application scope changes.
A14: V6.2 | B14: Password Security | C14: V6.2.8 | D14: Verify that the application verifies the user's password exactly as received from the user, without any modifications such as truncation or case transformation. | E14: 1 | F14: Compliant | G14: Automatically marked compliant from passing evidence: administrator MFA; account status validation; failed-login lockout behaviour. | H14: NFR-05; SR-01; SR-05; SR-07; AuthServiceTest; AuthControllerIntegrationTest; SystemFunctionalTests; MFA/TOTP code and tests detected | I14: Automatically inferred as implemented or justified from passing tests, source code, configuration, or build artifacts. | J14: Automated repository evidence | K14: AuthServiceTest; AuthControllerIntegrationTest; SystemFunctionalTests; MFA/TOTP code and tests detected | L14: administrator MFA; account status validation; failed-login lockout behaviour | M14: Keep make asvs-tracker passing; reassess if code, tests, or scope changes.
A15: V6.2 | B15: Password Security | C15: V6.2.9 | D15: Verify that passwords of at least 64 characters are permitted. | E15: 2 | F15: Compliant | G15: Automatically marked compliant from passing evidence: administrator MFA; account status validation; failed-login lockout behaviour. | H15: SR-01; SR-05; SR-07; AuthServiceTest; AuthControllerIntegrationTest; SystemFunctionalTests; MFA/TOTP code and tests detected | I15: Automatically inferred as implemented or justified from passing tests, source code, configuration, or build artifacts. | J15: Automated repository evidence | K15: AuthServiceTest; AuthControllerIntegrationTest; SystemFunctionalTests; MFA/TOTP code and tests detected | L15: administrator MFA; account status validation; failed-login lockout behaviour | M15: Keep make asvs-tracker passing; reassess if code, tests, or scope changes.
A16: V6.2 | B16: Password Security | C16: V6.2.10 | D16: Verify that a user's password stays valid until it is discovered to be compromised or the user rotates it. The application must not require periodic credential rotation. | E16: 2 | F16: Compliant | G16: Automatically marked compliant from passing evidence: administrator MFA; account status validation; failed-login lockout behaviour. | H16: SR-01; SR-05; SR-07; AuthServiceTest; AuthControllerIntegrationTest; SystemFunctionalTests; MFA/TOTP code and tests detected | I16: Automatically inferred as implemented or justified from passing tests, source code, configuration, or build artifacts. | J16: Automated repository evidence | K16: AuthServiceTest; AuthControllerIntegrationTest; SystemFunctionalTests; MFA/TOTP code and tests detected | L16: administrator MFA; account status validation; failed-login lockout behaviour | M16: Keep make asvs-tracker passing; reassess if code, tests, or scope changes.
A17: V6.2 | B17: Password Security | C17: V6.2.11 | D17: Verify that the documented list of context specific words is used to prevent easy to guess passwords being created. | E17: 2 | F17: Compliant | G17: Automatically marked compliant from passing evidence: administrator MFA; account status validation; failed-login lockout behaviour. | H17: SR-01; SR-05; SR-07; AuthServiceTest; AuthControllerIntegrationTest; SystemFunctionalTests; MFA/TOTP code and tests detected | I17: Automatically inferred as implemented or justified from passing tests, source code, configuration, or build artifacts. | J17: Automated repository evidence | K17: AuthServiceTest; AuthControllerIntegrationTest; SystemFunctionalTests; MFA/TOTP code and tests detected | L17: administrator MFA; account status validation; failed-login lockout behaviour | M17: Keep make asvs-tracker passing; reassess if code, tests, or scope changes.
A18: V6.2 | B18: Password Security | C18: V6.2.12 | D18: Verify that passwords submitted during account registration or password changes are checked against a set of breached passwords. | E18: 2 | F18: Compliant | G18: Automatically marked compliant from passing evidence: administrator MFA; account status validation; failed-login lockout behaviour. | H18: SR-01; SR-05; SR-07; AuthServiceTest; AuthControllerIntegrationTest; SystemFunctionalTests; MFA/TOTP code and tests detected | I18: Automatically inferred as implemented or justified from passing tests, source code, configuration, or build artifacts. | J18: Automated repository evidence | K18: AuthServiceTest; AuthControllerIntegrationTest; SystemFunctionalTests; MFA/TOTP code and tests detected | L18: administrator MFA; account status validation; failed-login lockout behaviour | M18: Keep make asvs-tracker passing; reassess if code, tests, or scope changes.
A19: V6.3 | B19: General Authentication Security
A20: V6.3 | B20: General Authentication Security | C20: V6.3.1 | D20: Verify that controls to prevent attacks such as credential stuffing and password brute force are implemented according to the application's security documentation. | E20: 1 | F20: Compliant | G20: Automatically marked compliant from passing evidence: failed-login lockout behaviour; administrator MFA; account status validation. | H20: SR-07; NFR-07; SR-01; SR-05; AuthServiceTest; AuthControllerIntegrationTest; SystemFunctionalTests; MFA/TOTP code and tests detected | I20: Automatically inferred as implemented or justified from passing tests, source code, configuration, or build artifacts. | J20: Automated repository evidence | K20: AuthServiceTest; AuthControllerIntegrationTest; SystemFunctionalTests; MFA/TOTP code and tests detected | L20: failed-login lockout behaviour; administrator MFA; account status validation | M20: Keep make asvs-tracker passing; reassess if code, tests, or scope changes.
A21: V6.3 | B21: General Authentication Security | C21: V6.3.2 | D21: Verify that default user accounts (e.g., "root", "admin", or "sa") are not present in the application or are disabled. | E21: 1 | F21: Compliant | G21: Automatically marked compliant from passing evidence: administrator MFA; account status validation; failed-login lockout behaviour. | H21: SR-01; SR-05; SR-07; AuthServiceTest; AuthControllerIntegrationTest; SystemFunctionalTests; MFA/TOTP code and tests detected | I21: Automatically inferred as implemented or justified from passing tests, source code, configuration, or build artifacts. | J21: Automated repository evidence | K21: AuthServiceTest; AuthControllerIntegrationTest; SystemFunctionalTests; MFA/TOTP code and tests detected | L21: administrator MFA; account status validation; failed-login lockout behaviour | M21: Keep make asvs-tracker passing; reassess if code, tests, or scope changes.
A22: V6.3 | B22: General Authentication Security | C22: V6.3.3 | D22: Verify that either a multi-factor authentication mechanism or a combination of single-factor authentication mechanisms, must be used in order to access the application. For L3, one of the factors must be a hardware-based authentication mechanism which provides compromise and impersonation resistance against phishing attacks while verifying the intent to authenticate by requiring a user-initiated action (such as a button press on a FIDO hardware key or a mobile phone). Relaxing any of the considerations in this requirement requires a fully documented rationale and a comprehensive set of mitigating controls. | E22: 2 | F22: Compliant | G22: Automatically marked compliant from passing evidence: administrator MFA; account status validation; failed-login lockout behaviour. | H22: SR-01; SR-05; SR-07; AuthServiceTest; AuthControllerIntegrationTest; SystemFunctionalTests; MFA/TOTP code and tests detected | I22: Automatically inferred as implemented or justified from passing tests, source code, configuration, or build artifacts. | J22: Automated repository evidence | K22: AuthServiceTest; AuthControllerIntegrationTest; SystemFunctionalTests; MFA/TOTP code and tests detected | L22: administrator MFA; account status validation; failed-login lockout behaviour | M22: Keep make asvs-tracker passing; reassess if code, tests, or scope changes.
A23: V6.3 | B23: General Authentication Security | C23: V6.3.4 | D23: Verify that, if the application includes multiple authentication pathways, there are no undocumented pathways and that security controls and authentication strength are enforced consistently. | E23: 2 | F23: Compliant | G23: Automatically marked compliant from passing evidence: administrator MFA; user data access isolation; account status validation; failed-login lockout behaviour; path traversal and report sandboxing; unsafe path/link handling; path traversal abuse-case regression. | H23: SR-01; SR-08; NFR-15; SR-05; SR-07; SR-26; SR-27; AC-06; AuthServiceTest; AuthControllerIntegrationTest; RbacIntegrationTest; SystemFunctionalTests; PathValidatorImplTest; ReportDirectoryServiceImplTest; AbuseCaseRegressionTest; MFA/TOTP code and tests detected; Spring method security and RBAC annotations detected; path validation and report sandbox code detected | I23: Automatically inferred as implemented or justified from passing tests, source code, configuration, or build artifacts. | J23: Automated repository evidence | K23: AuthServiceTest; AuthControllerIntegrationTest; RbacIntegrationTest; SystemFunctionalTests; PathValidatorImplTest; ReportDirectoryServiceImplTest; AbuseCaseRegressionTest; MFA/TOTP code and tests detected; Spring method security and RBAC annotations detected; path validation and report sandbox code detected | L23: administrator MFA; user data access isolation; account status validation; failed-login lockout behaviour; path traversal and report sandboxing; unsafe path/link handling; path traversal abuse-case regression | M23: Keep make asvs-tracker passing; reassess if code, tests, or scope changes.
A24: V6.3 | B24: General Authentication Security | C24: V6.3.5 | D24: Verify that users are notified of suspicious authentication attempts (successful or unsuccessful). This may include authentication attempts from an unusual location or client, partially successful authentication (only one of multiple factors), an authentication attempt after a long period of inactivity or a successful authentication after several unsuccessful attempts. | E24: 3 | F24: Compliant | G24: Automatically marked compliant from passing evidence: administrator MFA; account status validation; failed-login lockout behaviour. | H24: SR-44; SR-01; SR-05; SR-07; AuthServiceTest; AuthControllerIntegrationTest; SystemFunctionalTests; MFA/TOTP code and tests detected | I24: Automatically inferred as implemented or justified from passing tests, source code, configuration, or build artifacts. | J24: Automated repository evidence | K24: AuthServiceTest; AuthControllerIntegrationTest; SystemFunctionalTests; MFA/TOTP code and tests detected | L24: administrator MFA; account status validation; failed-login lockout behaviour | M24: Keep make asvs-tracker passing; reassess if code, tests, or scope changes.
A25: V6.3 | B25: General Authentication Security | C25: V6.3.6 | D25: Verify that email is not used as either a single-factor or multi-factor authentication mechanism. | E25: 3 | F25: Compliant | G25: Automatically marked compliant from passing evidence: administrator MFA; account status validation; failed-login lockout behaviour. | H25: SR-01; SR-05; SR-07; AuthServiceTest; AuthControllerIntegrationTest; SystemFunctionalTests; MFA/TOTP code and tests detected | I25: Automatically inferred as implemented or justified from passing tests, source code, configuration, or build artifacts. | J25: Automated repository evidence | K25: AuthServiceTest; AuthControllerIntegrationTest; SystemFunctionalTests; MFA/TOTP code and tests detected | L25: administrator MFA; account status validation; failed-login lockout behaviour | M25: Keep make asvs-tracker passing; reassess if code, tests, or scope changes.
A26: V6.3 | B26: General Authentication Security | C26: V6.3.7 | D26: Verify that users are notified after updates to authentication details, such as credential resets or modification of the username or email address. | E26: 3 | F26: Compliant | G26: Automatically marked compliant from passing evidence: role-change audit logging; administrator MFA; account status validation; failed-login lockout behaviour. | H26: SR-39; SR-01; SR-05; SR-07; AuditLoggerTest; RbacIntegrationTest; AuthServiceTest; AuthControllerIntegrationTest; SystemFunctionalTests; MFA/TOTP code and tests detected; audit logging implementation detected | I26: Automatically inferred as implemented or justified from passing tests, source code, configuration, or build artifacts. | J26: Automated repository evidence | K26: AuditLoggerTest; RbacIntegrationTest; AuthServiceTest; AuthControllerIntegrationTest; SystemFunctionalTests; MFA/TOTP code and tests detected; audit logging implementation detected | L26: role-change audit logging; administrator MFA; account status validation; failed-login lockout behaviour | M26: Keep make asvs-tracker passing; reassess if code, tests, or scope changes.
A27: V6.3 | B27: General Authentication Security | C27: V6.3.8 | D27: Verify that valid users cannot be deduced from failed authentication challenges, such as by basing on error messages, HTTP response codes, or different response times. Registration and forgot password functionality must also have this protection. | E27: 3 | F27: Compliant | G27: Automatically marked compliant from passing evidence: administrator MFA; account status validation; failed-login lockout behaviour; authentication audit logging; sensitive log data checks; safe error response checks. | H27: SR-01; SR-05; SR-07; SR-37; SR-45; SR-46; AuthServiceTest; AuthControllerIntegrationTest; SystemFunctionalTests; AuditLoggerTest; GlobalExceptionHandlerTest; ControllerIntegrationTests; MFA/TOTP code and tests detected; audit logging implementation detected; centralized safe error handling detected | I27: Automatically inferred as implemented or justified from passing tests, source code, configuration, or build artifacts. | J27: Automated repository evidence | K27: AuthServiceTest; AuthControllerIntegrationTest; SystemFunctionalTests; AuditLoggerTest; GlobalExceptionHandlerTest; ControllerIntegrationTests; MFA/TOTP code and tests detected; audit logging implementation detected; centralized safe error handling detected | L27: administrator MFA; account status validation; failed-login lockout behaviour; authentication audit logging; sensitive log data checks; safe error response checks | M27: Keep make asvs-tracker passing; reassess if code, tests, or scope changes.
A28: V6.4 | B28: Authentication Factor Lifecycle and Recovery
A29: V6.4 | B29: Authentication Factor Lifecycle and Recovery | C29: V6.4.1 | D29: Verify that system generated initial passwords or activation codes are securely randomly generated, follow the existing password policy, and expire after a short period of time or after they are initially used. These initial secrets must not be permitted to become the long term password. | E29: 1 | F29: N/A | G29: Automatically marked out of scope: No browser-rendered frontend surface is present in this repository. | H29: Automated scope inference | I29: Out of scope for VendNet as currently implemented, or the requirement does not apply to this REST API/backend. | J29: Scope inference | K29: Not required for current backend scope. | L29: No browser-rendered frontend surface is present in this repository. | M29: Revisit if the application scope changes.
A30: V6.4 | B30: Authentication Factor Lifecycle and Recovery | C30: V6.4.2 | D30: Verify that password hints or knowledge-based authentication (so-called "secret questions") are not present. | E30: 1 | F30: Compliant | G30: Automatically marked compliant from passing evidence: administrator MFA; account status validation; failed-login lockout behaviour; secrets externalized through configuration; pinned dependency rules. | H30: SR-01; SR-05; SR-07; SR-11; SR-34; AuthServiceTest; AuthControllerIntegrationTest; SystemFunctionalTests; GitHub Actions secret scan; application-prod.properties; Maven Enforcer; pom.xml; MFA/TOTP code and tests detected; SCA/SBOM/enforcer configuration detected; CI secret/security scanning configuration detected | I30: Automatically inferred as implemented or justified from passing tests, source code, configuration, or build artifacts. | J30: Automated repository evidence | K30: AuthServiceTest; AuthControllerIntegrationTest; SystemFunctionalTests; GitHub Actions secret scan; application-prod.properties; Maven Enforcer; pom.xml; MFA/TOTP code and tests detected; SCA/SBOM/enforcer configuration detected; CI secret/security scanning configuration detected | L30: administrator MFA; account status validation; failed-login lockout behaviour; secrets externalized through configuration; pinned dependency rules | M30: Keep make asvs-tracker passing; reassess if code, tests, or scope changes.
A31: V6.4 | B31: Authentication Factor Lifecycle and Recovery | C31: V6.4.3 | D31: Verify that a secure process for resetting a forgotten password is implemented, that does not bypass any enabled multi-factor authentication mechanisms. | E31: 2 | F31: Compliant | G31: Automatically marked compliant from passing evidence: administrator MFA; account status validation; failed-login lockout behaviour. | H31: SR-01; SR-05; SR-07; AuthServiceTest; AuthControllerIntegrationTest; SystemFunctionalTests; MFA/TOTP code and tests detected | I31: Automatically inferred as implemented or justified from passing tests, source code, configuration, or build artifacts. | J31: Automated repository evidence | K31: AuthServiceTest; AuthControllerIntegrationTest; SystemFunctionalTests; MFA/TOTP code and tests detected | L31: administrator MFA; account status validation; failed-login lockout behaviour | M31: Keep make asvs-tracker passing; reassess if code, tests, or scope changes.
A32: V6.4 | B32: Authentication Factor Lifecycle and Recovery | C32: V6.4.4 | D32: Verify that if a multi-factor authentication factor is lost, evidence of identity proofing is performed at the same level as during enrollment. | E32: 2 | F32: Compliant | G32: Automatically marked compliant from passing evidence: administrator MFA; account status validation; failed-login lockout behaviour. | H32: SR-01; SR-05; SR-07; AuthServiceTest; AuthControllerIntegrationTest; SystemFunctionalTests; MFA/TOTP code and tests detected | I32: Automatically inferred as implemented or justified from passing tests, source code, configuration, or build artifacts. | J32: Automated repository evidence | K32: AuthServiceTest; AuthControllerIntegrationTest; SystemFunctionalTests; MFA/TOTP code and tests detected | L32: administrator MFA; account status validation; failed-login lockout behaviour | M32: Keep make asvs-tracker passing; reassess if code, tests, or scope changes.
A33: V6.4 | B33: Authentication Factor Lifecycle and Recovery | C33: V6.4.5 | D33: Verify that renewal instructions for authentication mechanisms which expire are sent with enough time to be carried out before the old authentication mechanism expires, configuring automated reminders if necessary. | E33: 3 | F33: Compliant | G33: Automatically marked compliant from passing evidence: JWT key strength and server-side signing; administrator MFA; account status validation; failed-login lockout behaviour. | H33: SR-04; SR-01; SR-05; SR-07; JwtServiceTest; JwtAuthenticationFilterTest; AuthServiceTest; AuthControllerIntegrationTest; SystemFunctionalTests; JWT service and signing/filter code detected; MFA/TOTP code and tests detected | I33: Automatically inferred as implemented or justified from passing tests, source code, configuration, or build artifacts. | J33: Automated repository evidence | K33: JwtServiceTest; JwtAuthenticationFilterTest; AuthServiceTest; AuthControllerIntegrationTest; SystemFunctionalTests; JWT service and signing/filter code detected; MFA/TOTP code and tests detected | L33: JWT key strength and server-side signing; administrator MFA; account status validation; failed-login lockout behaviour | M33: Keep make asvs-tracker passing; reassess if code, tests, or scope changes.
A34: V6.4 | B34: Authentication Factor Lifecycle and Recovery | C34: V6.4.6 | D34: Verify that administrative users can initiate the password reset process for the user, but that this does not allow them to change or choose the user's password. This prevents a situation where they know the user's password. | E34: 3 | F34: Compliant | G34: Automatically marked compliant from passing evidence: administrator MFA; account status validation; failed-login lockout behaviour. | H34: SR-01; SR-05; SR-07; AuthServiceTest; AuthControllerIntegrationTest; SystemFunctionalTests; MFA/TOTP code and tests detected | I34: Automatically inferred as implemented or justified from passing tests, source code, configuration, or build artifacts. | J34: Automated repository evidence | K34: AuthServiceTest; AuthControllerIntegrationTest; SystemFunctionalTests; MFA/TOTP code and tests detected | L34: administrator MFA; account status validation; failed-login lockout behaviour | M34: Keep make asvs-tracker passing; reassess if code, tests, or scope changes.
A35: V6.5 | B35: General Multi-factor authentication requirements
A36: V6.5 | B36: General Multi-factor authentication requirements | C36: V6.5.1 | D36: Verify that lookup secrets, out-of-band authentication requests or codes, and time-based one-time passwords (TOTPs) are only successfully usable once. | E36: 2 | F36: Compliant | G36: Automatically marked compliant from passing evidence: administrator MFA; account status validation; failed-login lockout behaviour; secrets externalized through configuration; pinned dependency rules. | H36: SR-01; SR-05; SR-07; SR-11; SR-34; AuthServiceTest; AuthControllerIntegrationTest; SystemFunctionalTests; GitHub Actions secret scan; application-prod.properties; Maven Enforcer; pom.xml; MFA/TOTP code and tests detected; SCA/SBOM/enforcer configuration detected; CI secret/security scanning configuration detected | I36: Automatically inferred as implemented or justified from passing tests, source code, configuration, or build artifacts. | J36: Automated repository evidence | K36: AuthServiceTest; AuthControllerIntegrationTest; SystemFunctionalTests; GitHub Actions secret scan; application-prod.properties; Maven Enforcer; pom.xml; MFA/TOTP code and tests detected; SCA/SBOM/enforcer configuration detected; CI secret/security scanning configuration detected | L36: administrator MFA; account status validation; failed-login lockout behaviour; secrets externalized through configuration; pinned dependency rules | M36: Keep make asvs-tracker passing; reassess if code, tests, or scope changes.
A37: V6.5 | B37: General Multi-factor authentication requirements | C37: V6.5.2 | D37: Verify that, when being stored in the application's backend, lookup secrets with less than 112 bits of entropy (19 random alphanumeric characters or 34 random digits) are hashed with an approved password storage hashing algorithm that incorporates a 32-bit random salt. A standard hash function can be used if the secret has 112 bits of entropy or more. | E37: 2 | F37: N/A | G37: Automatically marked out of scope: No browser-rendered frontend surface is present in this repository. | H37: Automated scope inference | I37: Out of scope for VendNet as currently implemented, or the requirement does not apply to this REST API/backend. | J37: Scope inference | K37: Not required for current backend scope. | L37: No browser-rendered frontend surface is present in this repository. | M37: Revisit if the application scope changes.
A38: V6.5 | B38: General Multi-factor authentication requirements | C38: V6.5.3 | D38: Verify that lookup secrets, out-of-band authentication code, and time-based one-time password seeds, are generated using a Cryptographically Secure Pseudorandom Number Generator (CSPRNG) to avoid predictable values. | E38: 2 | F38: N/A | G38: Automatically marked out of scope: No browser-rendered frontend surface is present in this repository. | H38: Automated scope inference | I38: Out of scope for VendNet as currently implemented, or the requirement does not apply to this REST API/backend. | J38: Scope inference | K38: Not required for current backend scope. | L38: No browser-rendered frontend surface is present in this repository. | M38: Revisit if the application scope changes.
A39: V6.5 | B39: General Multi-factor authentication requirements | C39: V6.5.4 | D39: Verify that lookup secrets and out-of-band authentication codes have a minimum of 20 bits of entropy (typically 4 random alphanumeric characters or 6 random digits is sufficient). | E39: 2 | F39: N/A | G39: Automatically marked out of scope: No browser-rendered frontend surface is present in this repository. | H39: Automated scope inference | I39: Out of scope for VendNet as currently implemented, or the requirement does not apply to this REST API/backend. | J39: Scope inference | K39: Not required for current backend scope. | L39: No browser-rendered frontend surface is present in this repository. | M39: Revisit if the application scope changes.
A40: V6.5 | B40: General Multi-factor authentication requirements | C40: V6.5.5 | D40: Verify that out-of-band authentication requests, codes, or tokens, as well as time-based one-time passwords (TOTPs) have a defined lifetime. Out of band requests must have a maximum lifetime of 10 minutes and for TOTP a maximum lifetime of 30 seconds. | E40: 2 | F40: Compliant | G40: Automatically marked compliant from passing evidence: administrator MFA; JWT signature and algorithm validation; JWT key strength and server-side signing; account status validation; failed-login lockout behaviour. | H40: SR-01; SR-03; SR-04; SR-05; SR-07; AuthServiceTest; AuthControllerIntegrationTest; AbuseCaseRegressionTest; JwtServiceTest; JwtAuthenticationFilterTest; SystemFunctionalTests; JWT service and signing/filter code detected; MFA/TOTP code and tests detected | I40: Automatically inferred as implemented or justified from passing tests, source code, configuration, or build artifacts. | J40: Automated repository evidence | K40: AuthServiceTest; AuthControllerIntegrationTest; AbuseCaseRegressionTest; JwtServiceTest; JwtAuthenticationFilterTest; SystemFunctionalTests; JWT service and signing/filter code detected; MFA/TOTP code and tests detected | L40: administrator MFA; JWT signature and algorithm validation; JWT key strength and server-side signing; account status validation; failed-login lockout behaviour | M40: Keep make asvs-tracker passing; reassess if code, tests, or scope changes.
A41: V6.5 | B41: General Multi-factor authentication requirements | C41: V6.5.6 | D41: Verify that any authentication factor (including physical devices) can be revoked in case of theft or other loss. | E41: 3 | F41: Compliant | G41: Automatically marked compliant from passing evidence: administrator MFA; account status validation; failed-login lockout behaviour. | H41: SR-22; SR-01; SR-05; SR-07; AuthServiceTest; AuthControllerIntegrationTest; SystemFunctionalTests; MFA/TOTP code and tests detected | I41: Automatically inferred as implemented or justified from passing tests, source code, configuration, or build artifacts. | J41: Automated repository evidence | K41: AuthServiceTest; AuthControllerIntegrationTest; SystemFunctionalTests; MFA/TOTP code and tests detected | L41: administrator MFA; account status validation; failed-login lockout behaviour | M41: Keep make asvs-tracker passing; reassess if code, tests, or scope changes.
A42: V6.5 | B42: General Multi-factor authentication requirements | C42: V6.5.7 | D42: Verify that biometric authentication mechanisms are only used as secondary factors together with either something you have or something you know. | E42: 3 | F42: Compliant | G42: Automatically marked compliant from passing evidence: administrator MFA; account status validation; failed-login lockout behaviour. | H42: SR-01; SR-05; SR-07; AuthServiceTest; AuthControllerIntegrationTest; SystemFunctionalTests; MFA/TOTP code and tests detected | I42: Automatically inferred as implemented or justified from passing tests, source code, configuration, or build artifacts. | J42: Automated repository evidence | K42: AuthServiceTest; AuthControllerIntegrationTest; SystemFunctionalTests; MFA/TOTP code and tests detected | L42: administrator MFA; account status validation; failed-login lockout behaviour | M42: Keep make asvs-tracker passing; reassess if code, tests, or scope changes.
A43: V6.5 | B43: General Multi-factor authentication requirements | C43: V6.5.8 | D43: Verify that time-based one-time passwords (TOTPs) are checked based on a time source from a trusted service and not from an untrusted or client provided time. | E43: 3 | F43: Compliant | G43: Automatically marked compliant from passing evidence: administrator MFA; account status validation; failed-login lockout behaviour. | H43: SR-01; SR-05; SR-07; AuthServiceTest; AuthControllerIntegrationTest; SystemFunctionalTests; MFA/TOTP code and tests detected | I43: Automatically inferred as implemented or justified from passing tests, source code, configuration, or build artifacts. | J43: Automated repository evidence | K43: AuthServiceTest; AuthControllerIntegrationTest; SystemFunctionalTests; MFA/TOTP code and tests detected | L43: administrator MFA; account status validation; failed-login lockout behaviour | M43: Keep make asvs-tracker passing; reassess if code, tests, or scope changes.
A44: V6.6 | B44: Out-of-Band authentication mechanisms
A45: V6.6 | B45: Out-of-Band authentication mechanisms | C45: V6.6.1 | D45: Verify that authentication mechanisms using the Public Switched Telephone Network (PSTN) to deliver One-time Passwords (OTPs) via phone or SMS are offered only when the phone number has previously been validated, alternate stronger methods (such as Time based One-time Passwords) are also offered, and the service provides information on their security risks to users. For L3 applications, phone and SMS must not be available as options. | E45: 2 | F45: Compliant | G45: Automatically marked compliant from passing evidence: administrator MFA; account status validation; failed-login lockout behaviour. | H45: SR-01; SR-05; SR-07; AuthServiceTest; AuthControllerIntegrationTest; SystemFunctionalTests; MFA/TOTP code and tests detected | I45: Automatically inferred as implemented or justified from passing tests, source code, configuration, or build artifacts. | J45: Automated repository evidence | K45: AuthServiceTest; AuthControllerIntegrationTest; SystemFunctionalTests; MFA/TOTP code and tests detected | L45: administrator MFA; account status validation; failed-login lockout behaviour | M45: Keep make asvs-tracker passing; reassess if code, tests, or scope changes.
A46: V6.6 | B46: Out-of-Band authentication mechanisms | C46: V6.6.2 | D46: Verify that out-of-band authentication requests, codes, or tokens are bound to the original authentication request for which they were generated and are not usable for a previous or subsequent one. | E46: 2 | F46: Compliant | G46: Automatically marked compliant from passing evidence: administrator MFA; JWT signature and algorithm validation; JWT key strength and server-side signing; account status validation; failed-login lockout behaviour. | H46: SR-01; SR-03; SR-04; SR-05; SR-07; AuthServiceTest; AuthControllerIntegrationTest; AbuseCaseRegressionTest; JwtServiceTest; JwtAuthenticationFilterTest; SystemFunctionalTests; JWT service and signing/filter code detected; MFA/TOTP code and tests detected | I46: Automatically inferred as implemented or justified from passing tests, source code, configuration, or build artifacts. | J46: Automated repository evidence | K46: AuthServiceTest; AuthControllerIntegrationTest; AbuseCaseRegressionTest; JwtServiceTest; JwtAuthenticationFilterTest; SystemFunctionalTests; JWT service and signing/filter code detected; MFA/TOTP code and tests detected | L46: administrator MFA; JWT signature and algorithm validation; JWT key strength and server-side signing; account status validation; failed-login lockout behaviour | M46: Keep make asvs-tracker passing; reassess if code, tests, or scope changes.
A47: V6.6 | B47: Out-of-Band authentication mechanisms | C47: V6.6.3 | D47: Verify that a code based out-of-band authentication mechanism is protected against brute force attacks by using rate limiting. Consider also using a code with at least 64 bits of entropy. | E47: 2 | F47: Compliant | G47: Automatically marked compliant from passing evidence: administrator MFA; account status validation; failed-login lockout behaviour. | H47: SR-01; NFR-07; SR-05; SR-07; AuthServiceTest; AuthControllerIntegrationTest; SystemFunctionalTests; MFA/TOTP code and tests detected | I47: Automatically inferred as implemented or justified from passing tests, source code, configuration, or build artifacts. | J47: Automated repository evidence | K47: AuthServiceTest; AuthControllerIntegrationTest; SystemFunctionalTests; MFA/TOTP code and tests detected | L47: administrator MFA; account status validation; failed-login lockout behaviour | M47: Keep make asvs-tracker passing; reassess if code, tests, or scope changes.
A48: V6.6 | B48: Out-of-Band authentication mechanisms | C48: V6.6.4 | D48: Verify that, where push notifications are used for multi-factor authentication, rate limiting is used to prevent push bombing attacks. Number matching may also mitigate this risk. | E48: 3 | F48: Compliant | G48: Automatically marked compliant from passing evidence: administrator MFA; account status validation; failed-login lockout behaviour. | H48: SR-01; SR-05; SR-07; AuthServiceTest; AuthControllerIntegrationTest; SystemFunctionalTests; MFA/TOTP code and tests detected | I48: Automatically inferred as implemented or justified from passing tests, source code, configuration, or build artifacts. | J48: Automated repository evidence | K48: AuthServiceTest; AuthControllerIntegrationTest; SystemFunctionalTests; MFA/TOTP code and tests detected | L48: administrator MFA; account status validation; failed-login lockout behaviour | M48: Keep make asvs-tracker passing; reassess if code, tests, or scope changes.
A49: V6.7 | B49: Cryptographic authentication mechanism
A50: V6.7 | B50: Cryptographic authentication mechanism | C50: V6.7.1 | D50: Verify that the certificates used to verify cryptographic authentication assertions are stored in a way protects them from modification. | E50: 3 | F50: Compliant | G50: Automatically marked compliant from passing evidence: administrator MFA; account status validation; failed-login lockout behaviour; TLS configuration; machine mTLS authentication paths. | H50: SR-22; SR-01; SR-05; SR-07; SR-17; SR-18; AuthServiceTest; AuthControllerIntegrationTest; SystemFunctionalTests; application-prod.properties; X509MachineAuthenticationFilterTest; TelemetryServiceTest; MFA/TOTP code and tests detected; X.509/mTLS machine authentication code detected | I50: Automatically inferred as implemented or justified from passing tests, source code, configuration, or build artifacts. | J50: Automated repository evidence | K50: AuthServiceTest; AuthControllerIntegrationTest; SystemFunctionalTests; application-prod.properties; X509MachineAuthenticationFilterTest; TelemetryServiceTest; MFA/TOTP code and tests detected; X.509/mTLS machine authentication code detected | L50: administrator MFA; account status validation; failed-login lockout behaviour; TLS configuration; machine mTLS authentication paths | M50: Keep make asvs-tracker passing; reassess if code, tests, or scope changes.
A51: V6.7 | B51: Cryptographic authentication mechanism | C51: V6.7.2 | D51: Verify that the challenge nonce is at least 64 bits in length, and statistically unique or unique over the lifetime of the cryptographic device. | E51: 3 | F51: Compliant | G51: Automatically marked compliant from passing evidence: administrator MFA; account status validation; failed-login lockout behaviour. | H51: SR-01; SR-05; SR-07; AuthServiceTest; AuthControllerIntegrationTest; SystemFunctionalTests; MFA/TOTP code and tests detected | I51: Automatically inferred as implemented or justified from passing tests, source code, configuration, or build artifacts. | J51: Automated repository evidence | K51: AuthServiceTest; AuthControllerIntegrationTest; SystemFunctionalTests; MFA/TOTP code and tests detected | L51: administrator MFA; account status validation; failed-login lockout behaviour | M51: Keep make asvs-tracker passing; reassess if code, tests, or scope changes.
A52: V6.8 | B52: Authentication with an Identity Provider
A53: V6.8 | B53: Authentication with an Identity Provider | C53: V6.8.1 | D53: Verify that, if the application supports multiple identity providers (IdPs), the user's identity cannot be spoofed via another supported identity provider (eg. by using the same user identifier). The standard mitigation would be for the application to register and identify the user using a combination of the IdP ID (serving as a namespace) and the user's ID in the IdP. | E53: 2 | F53: Compliant | G53: Automatically marked compliant from passing evidence: administrator MFA; account status validation; failed-login lockout behaviour. | H53: SR-01; SR-05; SR-07; AuthServiceTest; AuthControllerIntegrationTest; SystemFunctionalTests; MFA/TOTP code and tests detected | I53: Automatically inferred as implemented or justified from passing tests, source code, configuration, or build artifacts. | J53: Automated repository evidence | K53: AuthServiceTest; AuthControllerIntegrationTest; SystemFunctionalTests; MFA/TOTP code and tests detected | L53: administrator MFA; account status validation; failed-login lockout behaviour | M53: Keep make asvs-tracker passing; reassess if code, tests, or scope changes.
A54: V6.8 | B54: Authentication with an Identity Provider | C54: V6.8.2 | D54: Verify that the presence and integrity of digital signatures on authentication assertions (for example on JWTs or SAML assertions) are always validated, rejecting any assertions that are unsigned or have invalid signatures. | E54: 2 | F54: Compliant | G54: Automatically marked compliant from passing evidence: JWT signature and algorithm validation; JWT key strength and server-side signing; administrator MFA; account status validation; failed-login lockout behaviour. | H54: SR-03; SR-04; SR-01; SR-05; SR-07; AbuseCaseRegressionTest; JwtServiceTest; JwtAuthenticationFilterTest; AuthServiceTest; AuthControllerIntegrationTest; SystemFunctionalTests; JWT service and signing/filter code detected; MFA/TOTP code and tests detected | I54: Automatically inferred as implemented or justified from passing tests, source code, configuration, or build artifacts. | J54: Automated repository evidence | K54: AbuseCaseRegressionTest; JwtServiceTest; JwtAuthenticationFilterTest; AuthServiceTest; AuthControllerIntegrationTest; SystemFunctionalTests; JWT service and signing/filter code detected; MFA/TOTP code and tests detected | L54: JWT signature and algorithm validation; JWT key strength and server-side signing; administrator MFA; account status validation; failed-login lockout behaviour | M54: Keep make asvs-tracker passing; reassess if code, tests, or scope changes.
A55: V6.8 | B55: Authentication with an Identity Provider | C55: V6.8.3 | D55: Verify that SAML assertions are uniquely processed and used only once within the validity period to prevent replay attacks. | E55: 2 | F55: Compliant | G55: Automatically marked compliant from passing evidence: administrator MFA; account status validation; failed-login lockout behaviour. | H55: SR-01; SR-05; SR-07; AuthServiceTest; AuthControllerIntegrationTest; SystemFunctionalTests; MFA/TOTP code and tests detected | I55: Automatically inferred as implemented or justified from passing tests, source code, configuration, or build artifacts. | J55: Automated repository evidence | K55: AuthServiceTest; AuthControllerIntegrationTest; SystemFunctionalTests; MFA/TOTP code and tests detected | L55: administrator MFA; account status validation; failed-login lockout behaviour | M55: Keep make asvs-tracker passing; reassess if code, tests, or scope changes.
A56: V6.8 | B56: Authentication with an Identity Provider | C56: V6.8.4 | D56: Verify that, if an application uses a separate Identity Provider (IdP) and expects specific authentication strength, methods, or recentness for specific functions, the application verifies this using the information returned by the IdP. For example, if OIDC is used, this might be achieved by validating ID Token claims such as 'acr', 'amr', and 'auth_time' (if present). If the IdP does not provide this information, the application must have a documented fallback approach that assumes that the minimum strength authentication mechanism was used (for example, single-factor authentication using username and password). | E56: 2 | F56: Compliant | G56: Automatically marked compliant from passing evidence: administrator MFA; JWT signature and algorithm validation; JWT key strength and server-side signing; account status validation; failed-login lockout behaviour. | H56: SR-01; SR-03; SR-04; SR-05; SR-07; AuthServiceTest; AuthControllerIntegrationTest; AbuseCaseRegressionTest; JwtServiceTest; JwtAuthenticationFilterTest; SystemFunctionalTests; JWT service and signing/filter code detected; MFA/TOTP code and tests detected | I56: Automatically inferred as implemented or justified from passing tests, source code, configuration, or build artifacts. | J56: Automated repository evidence | K56: AuthServiceTest; AuthControllerIntegrationTest; AbuseCaseRegressionTest; JwtServiceTest; JwtAuthenticationFilterTest; SystemFunctionalTests; JWT service and signing/filter code detected; MFA/TOTP code and tests detected | L56: administrator MFA; JWT signature and algorithm validation; JWT key strength and server-side signing; account status validation; failed-login lockout behaviour | M56: Keep make asvs-tracker passing; reassess if code, tests, or scope changes.

Sheet V7 - Session Management
A1: Section ID | B1: Section Name | C1: Req ID | D1: Description | E1: Level | F1: Status | G1: Observations | H1: Reference / Link | I1: DX Status Meaning | J1: Evidence Type | K1: Automated Evidence | L1: Evidence Source | M1: Next Action
A2: V7.1 | B2: Session Management Documentation
A3: V7.1 | B3: Session Management Documentation | C3: V7.1.1 | D3: Verify that the user's session inactivity timeout and absolute maximum session lifetime are documented, are appropriate in combination with other controls, and that the documentation includes justification for any deviations from NIST SP 800-63B re-authentication requirements. | E3: 2 | F3: Compliant | G3: Automatically marked compliant from passing evidence: account status validation; administrator MFA; failed-login lockout behaviour. | H3: SR-05; SR-01; SR-07; AuthServiceTest; AuthControllerIntegrationTest; SystemFunctionalTests; MFA/TOTP code and tests detected | I3: Automatically inferred as implemented or justified from passing tests, source code, configuration, or build artifacts. | J3: Automated repository evidence | K3: AuthServiceTest; AuthControllerIntegrationTest; SystemFunctionalTests; MFA/TOTP code and tests detected | L3: account status validation; administrator MFA; failed-login lockout behaviour | M3: Keep make asvs-tracker passing; reassess if code, tests, or scope changes.
A4: V7.1 | B4: Session Management Documentation | C4: V7.1.2 | D4: Verify that the documentation defines how many concurrent (parallel) sessions are allowed for one account as well as the intended behaviors and actions to be taken when the maximum number of active sessions is reached. | E4: 2 | F4: Compliant | G4: Automatically marked compliant from passing evidence: account status validation; transaction and stock consistency; server-side price enforcement; stock limit validation; client-supplied price abuse-case regression; TOCTOU/stock race abuse-case regression. | H4: SR-05; SR-15; SR-24; SR-25; AC-03; AC-07; AuthServiceTest; AuthControllerIntegrationTest; SaleServiceTest; SlotServiceTest; AbuseCaseRegressionTest | I4: Automatically inferred as implemented or justified from passing tests, source code, configuration, or build artifacts. | J4: Automated repository evidence | K4: AuthServiceTest; AuthControllerIntegrationTest; SaleServiceTest; SlotServiceTest; AbuseCaseRegressionTest | L4: account status validation; transaction and stock consistency; server-side price enforcement; stock limit validation; client-supplied price abuse-case regression; TOCTOU/stock race abuse-case regression | M4: Keep make asvs-tracker passing; reassess if code, tests, or scope changes.
A5: V7.1 | B5: Session Management Documentation | C5: V7.1.3 | D5: Verify that all systems that create and manage user sessions as part of a federated identity management ecosystem (such as SSO systems) are documented along with controls to coordinate session lifetimes, termination, and any other conditions that require re-authentication. | E5: 2 | F5: Compliant | G5: Automatically marked compliant from passing evidence: administrator MFA; account status validation; failed-login lockout behaviour. | H5: SR-01; SR-05; SR-07; AuthServiceTest; AuthControllerIntegrationTest; SystemFunctionalTests; MFA/TOTP code and tests detected | I5: Automatically inferred as implemented or justified from passing tests, source code, configuration, or build artifacts. | J5: Automated repository evidence | K5: AuthServiceTest; AuthControllerIntegrationTest; SystemFunctionalTests; MFA/TOTP code and tests detected | L5: administrator MFA; account status validation; failed-login lockout behaviour | M5: Keep make asvs-tracker passing; reassess if code, tests, or scope changes.
A6: V7.2 | B6: Fundamental Session Management Security
A7: V7.2 | B7: Fundamental Session Management Security | C7: V7.2.1 | D7: Verify that the application performs all session token verification using a trusted, backend service. | E7: 1 | F7: Compliant | G7: Automatically marked compliant from passing evidence: JWT signature and algorithm validation; JWT key strength and server-side signing. | H7: SR-03; SR-04; AbuseCaseRegressionTest; JwtServiceTest; JwtAuthenticationFilterTest; JWT service and signing/filter code detected | I7: Automatically inferred as implemented or justified from passing tests, source code, configuration, or build artifacts. | J7: Automated repository evidence | K7: AbuseCaseRegressionTest; JwtServiceTest; JwtAuthenticationFilterTest; JWT service and signing/filter code detected | L7: JWT signature and algorithm validation; JWT key strength and server-side signing | M7: Keep make asvs-tracker passing; reassess if code, tests, or scope changes.
A8: V7.2 | B8: Fundamental Session Management Security | C8: V7.2.2 | D8: Verify that the application uses either self-contained or reference tokens that are dynamically generated for session management, i.e. not using static API secrets and keys. | E8: 1 | F8: Compliant | G8: Automatically marked compliant from passing evidence: JWT signature and algorithm validation; JWT key strength and server-side signing; secrets externalized through configuration; pinned dependency rules. | H8: SR-03; SR-04; SR-11; SR-34; AbuseCaseRegressionTest; JwtServiceTest; JwtAuthenticationFilterTest; GitHub Actions secret scan; application-prod.properties; Maven Enforcer; pom.xml; JWT service and signing/filter code detected; SCA/SBOM/enforcer configuration detected; CI secret/security scanning configuration detected | I8: Automatically inferred as implemented or justified from passing tests, source code, configuration, or build artifacts. | J8: Automated repository evidence | K8: AbuseCaseRegressionTest; JwtServiceTest; JwtAuthenticationFilterTest; GitHub Actions secret scan; application-prod.properties; Maven Enforcer; pom.xml; JWT service and signing/filter code detected; SCA/SBOM/enforcer configuration detected; CI secret/security scanning configuration detected | L8: JWT signature and algorithm validation; JWT key strength and server-side signing; secrets externalized through configuration; pinned dependency rules | M8: Keep make asvs-tracker passing; reassess if code, tests, or scope changes.
A9: V7.2 | B9: Fundamental Session Management Security | C9: V7.2.3 | D9: Verify that if reference tokens are used to represent user sessions, they are unique and generated using a cryptographically secure pseudo-random number generator (CSPRNG) and possess at least 128 bits of entropy. | E9: 1 | F9: N/A | G9: Automatically marked out of scope: No browser-rendered frontend surface is present in this repository. | H9: Automated scope inference | I9: Out of scope for VendNet as currently implemented, or the requirement does not apply to this REST API/backend. | J9: Scope inference | K9: Not required for current backend scope. | L9: No browser-rendered frontend surface is present in this repository. | M9: Revisit if the application scope changes.
A10: V7.2 | B10: Fundamental Session Management Security | C10: V7.2.4 | D10: Verify that the application generates a new session token on user authentication, including re-authentication, and terminates the current session token. | E10: 1 | F10: Compliant | G10: Automatically marked compliant from passing evidence: account status validation; JWT signature and algorithm validation; JWT key strength and server-side signing; administrator MFA; failed-login lockout behaviour. | H10: SR-05; SR-03; SR-04; SR-01; SR-07; AuthServiceTest; AuthControllerIntegrationTest; AbuseCaseRegressionTest; JwtServiceTest; JwtAuthenticationFilterTest; SystemFunctionalTests; JWT service and signing/filter code detected; MFA/TOTP code and tests detected | I10: Automatically inferred as implemented or justified from passing tests, source code, configuration, or build artifacts. | J10: Automated repository evidence | K10: AuthServiceTest; AuthControllerIntegrationTest; AbuseCaseRegressionTest; JwtServiceTest; JwtAuthenticationFilterTest; SystemFunctionalTests; JWT service and signing/filter code detected; MFA/TOTP code and tests detected | L10: account status validation; JWT signature and algorithm validation; JWT key strength and server-side signing; administrator MFA; failed-login lockout behaviour | M10: Keep make asvs-tracker passing; reassess if code, tests, or scope changes.
A11: V7.3 | B11: Session Timeout
A12: V7.3 | B12: Session Timeout | C12: V7.3.1 | D12: Verify that there is an inactivity timeout such that re-authentication is enforced according to risk analysis and documented security decisions. | E12: 2 | F12: Compliant | G12: Automatically marked compliant from passing evidence: account status validation; administrator MFA; failed-login lockout behaviour. | H12: SR-05; SR-01; SR-07; AuthServiceTest; AuthControllerIntegrationTest; SystemFunctionalTests; MFA/TOTP code and tests detected | I12: Automatically inferred as implemented or justified from passing tests, source code, configuration, or build artifacts. | J12: Automated repository evidence | K12: AuthServiceTest; AuthControllerIntegrationTest; SystemFunctionalTests; MFA/TOTP code and tests detected | L12: account status validation; administrator MFA; failed-login lockout behaviour | M12: Keep make asvs-tracker passing; reassess if code, tests, or scope changes.
A13: V7.3 | B13: Session Timeout | C13: V7.3.2 | D13: Verify that there is an absolute maximum session lifetime such that re-authentication is enforced according to risk analysis and documented security decisions. | E13: 2 | F13: Compliant | G13: Automatically marked compliant from passing evidence: account status validation; administrator MFA; failed-login lockout behaviour. | H13: SR-05; SR-01; SR-07; AuthServiceTest; AuthControllerIntegrationTest; SystemFunctionalTests; MFA/TOTP code and tests detected | I13: Automatically inferred as implemented or justified from passing tests, source code, configuration, or build artifacts. | J13: Automated repository evidence | K13: AuthServiceTest; AuthControllerIntegrationTest; SystemFunctionalTests; MFA/TOTP code and tests detected | L13: account status validation; administrator MFA; failed-login lockout behaviour | M13: Keep make asvs-tracker passing; reassess if code, tests, or scope changes.
A14: V7.4 | B14: Session Termination
A15: V7.4 | B15: Session Termination | C15: V7.4.1 | D15: Verify that when session termination is triggered (such as logout or expiration), the application disallows any further use of the session. For reference tokens or stateful sessions, this means invalidating the session data at the application backend. Applications using self-contained tokens will need a solution such as maintaining a list of terminated tokens, disallowing tokens produced before a per-user date and time or rotating a per-user signing key. | E15: 1 | F15: Compliant | G15: Automatically marked compliant from passing evidence: account status validation; JWT signature and algorithm validation; JWT key strength and server-side signing; authentication audit logging; sensitive log data checks; safe error response checks. | H15: SR-05; SR-03; SR-04; SR-37; SR-45; SR-46; AuthServiceTest; AuthControllerIntegrationTest; AbuseCaseRegressionTest; JwtServiceTest; JwtAuthenticationFilterTest; AuditLoggerTest; GlobalExceptionHandlerTest; ControllerIntegrationTests; JWT service and signing/filter code detected; audit logging implementation detected; centralized safe error handling detected | I15: Automatically inferred as implemented or justified from passing tests, source code, configuration, or build artifacts. | J15: Automated repository evidence | K15: AuthServiceTest; AuthControllerIntegrationTest; AbuseCaseRegressionTest; JwtServiceTest; JwtAuthenticationFilterTest; AuditLoggerTest; GlobalExceptionHandlerTest; ControllerIntegrationTests; JWT service and signing/filter code detected; audit logging implementation detected; centralized safe error handling detected | L15: account status validation; JWT signature and algorithm validation; JWT key strength and server-side signing; authentication audit logging; sensitive log data checks; safe error response checks | M15: Keep make asvs-tracker passing; reassess if code, tests, or scope changes.
A16: V7.4 | B16: Session Termination | C16: V7.4.2 | D16: Verify that the application terminates all active sessions when a user account is disabled or deleted (such as an employee leaving the company). | E16: 1 | F16: Compliant | G16: Automatically marked compliant from passing evidence: account status validation. | H16: SR-05; AuthServiceTest; AuthControllerIntegrationTest | I16: Automatically inferred as implemented or justified from passing tests, source code, configuration, or build artifacts. | J16: Automated repository evidence | K16: AuthServiceTest; AuthControllerIntegrationTest | L16: account status validation | M16: Keep make asvs-tracker passing; reassess if code, tests, or scope changes.
A17: V7.4 | B17: Session Termination | C17: V7.4.3 | D17: Verify that the application gives the option to terminate all other active sessions after a successful change or removal of any authentication factor (including password change via reset or recovery and, if present, an MFA settings update). | E17: 2 | F17: Compliant | G17: Automatically marked compliant from passing evidence: role-change audit logging; administrator MFA; account status validation; failed-login lockout behaviour. | H17: SR-39; SR-01; SR-05; SR-07; AuditLoggerTest; RbacIntegrationTest; AuthServiceTest; AuthControllerIntegrationTest; SystemFunctionalTests; MFA/TOTP code and tests detected; audit logging implementation detected | I17: Automatically inferred as implemented or justified from passing tests, source code, configuration, or build artifacts. | J17: Automated repository evidence | K17: AuditLoggerTest; RbacIntegrationTest; AuthServiceTest; AuthControllerIntegrationTest; SystemFunctionalTests; MFA/TOTP code and tests detected; audit logging implementation detected | L17: role-change audit logging; administrator MFA; account status validation; failed-login lockout behaviour | M17: Keep make asvs-tracker passing; reassess if code, tests, or scope changes.
